{
	"名称": "厦门港务",
	"code": "000905",
	"全名": "厦门港务发展股份有限公司",
	"地域": "福建省",
	"分类": "小盘股",
	"财务": "",
	"行业": "交通运输—港口航运",
	"业务": "以港口为依托的综合物流业务以及件散杂货、内贸集装箱的装卸、堆存、仓储、助轮船靠离泊以及贸易、建材等业务",
	"产品": "码头业务、建材销售、代理相关业务、拖轮助靠业务、运输劳务、贸易业务、理货业务、物流延伸服务及其他",
	"概念": "福建自贸区，一带一路，融资融券，自由贸易港",
	"概念y": "中证1000-100%  美丽厦门-90%  港口-87%  厦门国资-87%  福建自贸区-86%  平潭免税区-73%  厦门自贸区-67%  邮轮旅游-59%  内河水运-44%  集装箱-38%  海峡西岸-34%  一带一路-28%  海峡邮轮经济圈-11%  双百企业-10%  险资举牌-8%  深港通-2%",
	"概念详情": {
		"福建自贸区": "国企,实控人厦门国资委,主营港口业务,厦门最大的港口码头运营商,公司的业务受益于海西自贸区的发展。",
		"一带一路": "公司拥有东南沿海实力最强的国际船舶代理企业、全省规模最大的散杂货装卸码头、厦门港唯一的内贸集装箱装卸码头、福建省规模最大的集装箱运输车队、厦门港唯一提供海上专业拖轮服务的企业和先进的物流信息管理系统。福建为海上丝绸之路核心区,“一带一路”倡议提出以来,厦门港已经与马来西亚巴生港、美国迈阿密港结成友好港,目前永久友好港已达11个。",
		"自由贸易港": "公司业务贯穿货物进出港所涉及的各个环节，构成了完整的港口综合物流服务供应链。"
	}
}