{
	"名称": "滨江集团",
	"code": "002244",
	"全名": "杭州滨江房产集团股份有限公司",
	"地域": "浙江省",
	"分类": "中盘股",
	"财务": "破净股",
	"行业": "房地产—房地产开发",
	"业务": "房地产开发及其延伸业务的经营。",
	"产品": "房地产、酒店、物业服务",
	"概念": "杭州亚运会，特色小镇，上海自贸区，杭州湾大湾区，互联网+，融资融券，深股通，租售同权",
	"概念y": "中证500-100%  深证成指-100%  杭州亚运会-14%  深港通-6%  上海自贸区-5%  杭州G20-5%  互联网+-0%",
	"概念详情": {
		"杭州亚运会": "公司为杭州本地地产公司，主营房地产开发及其延伸业务的经营。",
		"特色小镇": "后续有望在适合时机将参与雄安新区周边小镇的项目开发;9月14日,公司以22.95亿元获得杭州地块,面积4为.63万平方米;该地块折后楼面价1.98万元/平方米,自持比例31%。",
		"上海自贸区": "2015年5月11日晚间，滨江集团发布公告指出，公司拟以自有资金人民币5亿元，在上海自贸区设立全资子公司上海滨顺投资管理有限公司，经营范围包括投资管理，实业投资，投资咨询，商务信息咨询等。设立该子公司，旨在充分利用上海自贸区的政策优势，做强公司投资业务。",
		"互联网+": "2015年3月，公司将以10000万元通过增资扩股的方式投资沃安公司。沃安公司主营业务是根据海外客户（主要为北美的AXST公司，SBCK等）的需求，确定生产工厂、设计公司、自主采购原材料，并且完成采购、生产、销售、出口上下游供应链整体服务。合作方沃安实业系一家专业从事互联网电子产品生产，销售的公司。增资完成后，沃安实业、艾柯瑟伦和公司对沃安公司持股比例为63%、27%、10%。投资完成后，公司将首次对互联网电子类产品生产销售领域企业进行投资。",
		"租售同权": "滨江集团2017年10月17日在投资者互动平台上表示，未来公司计划积极推进长租公寓计划，充分发挥城市开发商和运营商的优势，力争成为杭州集中式长租公寓的市场龙头。滨江未来五到十年的产业布局战略是长租公寓+房地产+金融。"
	}
}