{
	"名称": "洋河股份",
	"code": "002304",
	"全名": "江苏洋河酒厂股份有限公司",
	"地域": "江苏省",
	"分类": "超大盘股",
	"财务": "权重股，一线蓝筹，绩优股",
	"行业": "食品饮料—饮料制造",
	"业务": "洋河、双沟系列白酒的生产和销售",
	"产品": "梦之蓝、洋河蓝色经典、双沟珍宝坊、洋河大曲、双沟大曲",
	"概念": "白酒概念，超级品牌，MSCI概念，大消费，融资融券，深股通",
	"概念y": "中证100-100%  沪深300-100%  白酒-19%  江苏沿海地区-10%  大消费-7%  深港通-6%  深证成指-5%  中小板指-4%  葡萄酒-3%  O2O-0%",
	"概念详情": {
		"白酒概念": "国内中高端白酒龙头企业之一(行业第三),国内绵柔型白酒代表,第一家拥有双中华名酒品牌(“洋河”、“双沟”),其中高端产品为“梦之蓝M9”(52度1298元),核心销售品牌为蓝色经典→梦之蓝、天之蓝、海之蓝;17年相关营收191亿元。",
		"超级品牌": "江苏洋河酒厂股份有限公司是一家大型酿酒企业,主要从事洋河蓝色经典、洋河大曲、敦煌古酿等系列品牌浓香型白酒的生产、加工和销售,产品具有\"甜、绵、软、净、香\"的绵柔型风格。\"洋河\"商标被国家工商总局评定为\"中国驰名商标\",产品获\"江苏省重点名牌产品\"。在其中由原轻工业部主办的1979年第三届全国评酒会上,洋河大曲酒与茅台、五粮液、汾酒等并列为白酒类国家八大名酒。",
		"O2O概念": "洋河股份（002304）2015年将在稳定发展白酒主业的同时，将大力推进互联网化转型。公司已制定了以O2O模式和B2C模式为核心的互联网化转型工程的详细规划，并进行相应的人事安排。在互联网规划上，公司以B2C模式和O2O模式为两大突破口。在B2C模式中，公司将继续以天猫、京东旗舰店为窗口，进一步丰富电商渠道产品线，扩大洋河在主流B2C平台的品牌占有率。在O2O模式中，公司将以“洋河1号”APP为平台，打造百城万店、微店分销、跨界合作三大工程。",
		"MSCI概念": "公司主营业务洋河、双沟系列白酒的生产和销售,为权重股、一线蓝筹、绩优股，被MSCI指数纳为样本股。"
	}
}