{
	"名称": "德赛西威",
	"code": "002920",
	"全名": "惠州市德赛西威汽车电子股份有限公司",
	"地域": "广东省",
	"分类": "小盘股",
	"财务": "白马股",
	"行业": "交运设备—汽车零部件",
	"业务": "汽车电子产品的研发设计、生产和销售",
	"产品": "车载信息娱乐系统、车载空调控制器、驾驶信息显示系统",
	"概念": "百度概念，无人驾驶，车联网，白马股，北汽新能源，汽车电子，深股通，蔚来汽车概念，养老金持股",
	"概念y": "汽配-6%",
	"概念详情": {
		"百度概念": "公司为Apollo首批成员,并深度参与百度BCU、DuerOS的共同研发。",
		"无人驾驶": "公司已布局智能驾驶及车联网,并已经掌握智能驾驶辅助系统中的自动紧急刹车、高速路自动巡航、自动泊车的量产技术;与小鹏汽车研发L3自动驾驶,2020年量产落地。",
		"车联网": "德赛西威在CESAsia2018(2018亚洲消费电子展)正式发布车联网战略。董事长陈春霖在战略发布会中提到：上市以来，公司不断加大在智能网联产品上的投入，车联网战略现已是德赛西威战略布局和实施的重要举措之一，公司力争在2020年打造出百万级的车联网用户平台。",
		"汽车电子": "公司利用自身在汽车电子软硬件的研发、系统整合与制造优势，在2016年正式成立了智能驾驶辅助事业单元，在智能驾驶领域进行了较为全面的部署。目前，在感知、决策、控制各个领域都已投入资源，涉及研发技术领域包括车道保持、自动泊车、前碰撞预警、自动紧急刹车、盲区监测、低速移动物体检测、行人识别等，其中部分技术已实现产品化。公司开发的包括算法、硬件在内的智能驾驶辅助产品已在2017年实现量产并交付。",
		"白马股": "截止最新一期报告期，该股营业总收入复合年增长率为31.61%,归属母公司股东的净利润复合年增长率为55%。",
		"北汽新能源": "公司2018年3月15日在投资者互动平台表示，广汽集团、北汽新能源、吉利汽车、蔚来汽车为公司客户。"
	}
}