{
	"名称": "通合科技",
	"code": "300491",
	"全名": "石家庄通合电子科技股份有限公司",
	"地域": "河北省",
	"分类": "小盘股",
	"财务": "",
	"行业": "机械设备—电气设备",
	"业务": "高频开关电源及相关电子产品的研发、生产和销售。",
	"产品": "充换电站充电电源系统(充电桩)、电动汽车车载电源、电力操作电源",
	"概念": "智能电网，充电桩，雄安新区，军工，汽车电子，新能源汽车",
	"概念y": "无线充电-100%  充电桩-53%  新能源汽车-15%  智能电网-11%",
	"概念详情": {
		"智能电网": "公司主要从事高频开关电源及相关电子产品的研发，生产和销售，产品包含电力操作电源模块和电力操作电源系统，电动汽车车载电源及充换电站充电电源系统和其他电源，广泛应用于智能电网，电动汽车和充换电站等多个领域。",
		"充电桩": "拥有充换电站充电电源系统(充电桩)高功率密度新型充电模块和整机系统;拥有超过600家客户,最早涉足国内充电桩及电动汽车车载电源领域的企业之一;充电桩类产品营收占比54%。公司致力于充换电站充电电源系统(充电桩)高功率密度新型充电模块和整机系统、电动汽车车载电源和电控产品的研制和推广，为公司在新能源市场上开创新局面提供有力的技术和产品支持。2017年，公司募投项目建设完成，研发条件极大改善，成立新能源汽车电力变换技术河北省工程实验室，公司技术中心被认定为省企业技术中心。公司拥有超过600家客户，其中包含鲁能智能，国电南瑞，国网普瑞特等知名电力设备厂商及宇通客车，福田汽车等大型整车制造商。公司为“国家电网上海高科充电站”，“国家电网湖北襄阳停堡场充电站”，“国家电网成都红旗充电站”，“国家电网成都槐树店充电站”，“国家电网成都龙泉充电站”，“国家电网宁夏丰登充换电站”，“上海嘉定叶城路换电站”，“赣州章江新区换电站”等项目建设提供了充电电源系统及相关产品.",
		"雄安新区": "注册地石家庄,当地充电桩设备龙头,已在河北交付了一定数量的新能源汽车充电设备,未来有望受益区域新能源设备增量预期。",
		"新能源汽车": "拥有充换电站充电电源系统(充电桩)高功率密度新型充电模块和整机系统;拥有超过600家客户,最早涉足国内充电桩及电动汽车车载电源领域的企业之一;充电桩类产品营收占比54%。",
		"汽车电子": "公司专注于高频开关电源技术的研发与创新，产品已涉及充换电站充电电源系统(充电桩)及电动汽车车载电源、电力操作电源模块和电力操作电源系统等多个领域，销售网络遍及全国20多个省市自治区，产品远销海外。",
		"军工": "2018年7月6日公司午间发布发行股份购买资产方案，拟以非公开发行股份的方式购买常程等3名自然人及霍威卓越合计持有的霍威电源100%的股权。本次交易标的资产霍威电源100%股权的交易价格确定为2.4亿元，全部以非公开发行股份的形式支付，发行价为14.95元/股。霍威电源自2010年成立以来专注于各类军工电源及电源模块的研发、生产与销售，具备完整的军工资质，熟悉军工市场，霍威电源与上市公司同属于电源领域。"
	}
}