{
	"名称": "格尔软件",
	"code": "603232",
	"全名": "格尔软件股份有限公司",
	"地域": "上海市",
	"分类": "小盘股",
	"财务": "",
	"行业": "信息服务—计算机应用",
	"业务": "以公钥基础设施PKI（PublicKeyInfrastructure）为核心的商用密码软件产品的研发、生产和销售及服务业务",
	"产品": "PKI安全应用产品、通用安全产品、PKI基础设施产品",
	"概念": "国产软件，网络安全",
	"概念y": "软件-54%  网络安全-40%  国产软件-37%",
	"概念详情": {
		"国产软件": "国内首批通过国家密码管理局审查、支持SM2算法的、省级电子认证服务机构的建设单位公司专注于信息安全行业PKI领域,主要从事以公钥基础设施PKI为核心的商用密码软件产品的研发、生产和销售及服务业务;公司的产品和技术已为政务、金融、军工、企业重要信息系统提供安全支撑与保障,参与承建了我国多个第三方数字认证中心系统,并在电子商务、互联网网络实名、金融电子支付、云计算平台、移动互联网、智慧城市等领域的业务安全发挥作用;17年软件行业收入272亿元,营收占比100%。",
		"网络安全": "公司自成立以来一直专注于信息安全行业PKI领域，主要从事以公钥基础设施PKI（PublicKeyInfrastructure）为核心的商用密码软件产品的研发、生产和销售及服务业务，为用户提供基于PKI的信息安全系列产品、安全服务和信息安全整体解决方案。",
		"高送转预期": "公司每股资本公积金较高(2.65元)，每股未分配利润较高(2.59元)，且总股本较小(0.85亿股)，有较强的高送转潜力。"
	}
}