{
	"名称": "派思股份",
	"code": "603318",
	"全名": "大连派思燃气系统股份有限公司",
	"地域": "辽宁省",
	"分类": "中盘股",
	"财务": "",
	"行业": "机械设备—专用设备",
	"业务": "燃气输配和燃气应用领域相关产品的设计、生产、销售和服务",
	"产品": "燃气设备、分布式能源服务、燃气运营、燃料贸易",
	"概念": "天然气，国资驰援，锂电池，股权转让",
	"概念y": "天然气-3%",
	"概念详情": {
		"天然气": "天然气发电成套设备供应商,在燃气运营方面,由控股孙公司雅安华燃等三家公司;7.2亿元投资了鄂尔多斯一期110×104Nm3/d天然气液化工厂项目,预计2018年12月完工投产;17年相关业务收入5.6亿元,主营占比超95%.",
		"锂电池": "正拓能源主要从事锂电池负极材料的研发，生产和销售，是国内的锂电池负极材料专业供应商之一，产品广泛用于消费电子类锂离子电池，动力锂离子电池和储能锂离子电池。本次交易完成后，公司主营业务在现有天然气产业链基础上将新增锂电池负极材料业务，进一步丰富上市公司在新能源领域的业务布局。"
	}
}