{
	"龙蟠科技_2021-11-01下午3_50_13_-龙蟠科技-603906": {
		"tradeInfoText": [],
		"tags": [],
		"system": [
			"6704841",
			"3379792"
		]
	},
	"青岛食品_2021-11-01下午4_38_47_-青岛食品-001219": {
		"tradeInfoText": [],
		"tags": [],
		"system": [
			"3762405"
		]
	},
	"文山电力_2021-11-01下午4_38_53_-文山电力-600995": {
		"tradeInfoText": [],
		"tags": [],
		"system": [
			"3379792",
			"1266517"
		]
	},
	"恒帅股份_2021-11-01下午4_39_17_-恒帅股份-300969": {
		"tradeInfoText": [],
		"tags": [],
		"system": [
			"3379792"
		]
	},
	"清水源_2021-11-01下午4_41_13_-清水源-300437": {
		"tags": [
			"2055992"
		],
		"system": [
			"3379792",
			"8415531",
			"2673493"
		],
		"tradeInfo": []
	},
	"金开新能_2021-11-01下午4_41_56_-金开新能-600821": {
		"system": [
			"3379792",
			"8415531"
		],
		"tradeInfo": []
	},
	"湖北宜化_2021-11-01下午4_42_09_-湖北宜化-000422": {
		"system": [
			"3379792",
			"8415531",
			"id_1743912644162_63267"
		],
		"tradeInfo": []
	},
	"海源复材_2021-11-01下午4_42_14_-海源复材-002529": {
		"system": [
			"3379792",
			"8415531",
			"0335063"
		],
		"tradeInfo": []
	},
	"亿利洁能_2021-11-01下午4_43_37_-亿利洁能-600277": {
		"tradeInfoText": [],
		"tags": [],
		"system": []
	},
	"宁德时代_2021-11-01下午4_43_52_-宁德时代-300750": {
		"system": [
			"3379792",
			"7458589"
		],
		"tradeInfo": []
	},
	"隆基股份_2021-11-01下午4_43_56_-隆基股份-601012": {
		"tradeInfoText": [],
		"tags": [],
		"system": [
			"7458589"
		]
	},
	"大金重工_2021-11-01下午4_44_27_-大金重工-002487": {
		"system": [
			"3379792",
			"8415531",
			"id_1722170897004_67020",
			"id_1743912644162_63267"
		],
		"tradeInfo": []
	},
	"东方电缆_2021-11-01下午4_44_35_-东方电缆-603606": {
		"tradeInfoText": [],
		"tags": [],
		"system": [
			"3379792"
		]
	},
	"晶澳科技_2021-11-01下午4_44_39_-晶澳科技-002459": {
		"tradeInfoText": [],
		"tags": [],
		"system": [
			"3589400",
			"3379792"
		]
	},
	"沧州明珠_2021-11-01下午4_44_46_-沧州明珠-002108": {
		"tradeInfoText": [],
		"tags": [],
		"system": [
			"3379792"
		]
	},
	"吉鑫科技_2021-11-01下午4_44_49_-吉鑫科技-601218": {
		"tradeInfoText": [],
		"tags": [],
		"system": [
			"3379792"
		]
	},
	"云天化_2021-11-01下午4_44_52_-云天化-600096": {
		"tradeInfoText": [],
		"tags": [],
		"system": [
			"3379792"
		]
	},
	"英维克_2021-11-01下午4_45_05_-英维克-002837": {
		"tradeInfoText": [],
		"tags": [],
		"system": [
			"3379792"
		]
	},
	"丰元股份_2021-11-01下午4_45_12_-丰元股份-002805": {
		"tradeInfoText": [],
		"tags": [],
		"system": [
			"3379792"
		]
	},
	"同力日升_2021-11-01下午4_45_15_-同力日升-605286": {
		"system": [
			"3379792",
			"2673493",
			"id_1743909850559_65502"
		],
		"tradeInfo": []
	},
	"爱康科技_2021-11-01下午4_45_20_-爱康科技-002610": {
		"system": [
			"3379792",
			"2673493"
		],
		"tradeInfo": [
			[
				"09:30:07",
				"卖出",
				"1600",
				"5.100"
			],
			[
				"09:30:17",
				"卖出",
				"1700",
				"5.080"
			]
		]
	},
	"高澜股份_2021-11-01下午4_45_24_-高澜股份-300499": {
		"tags": [],
		"system": []
	},
	"中青宝_2021-11-01下午4_45_27_-中青宝-300052": {
		"system": [
			"3379792",
			"2673493"
		],
		"tradeInfo": []
	},
	"恒润股份_2021-11-01下午4_51_55_-恒润股份-603985": {
		"system": [
			"3379792",
			"2673493"
		],
		"tradeInfo": []
	},
	"创业黑马_2021-11-01下午4_54_34_-创业黑马-300688": {
		"tradeInfoText": [],
		"tags": [],
		"system": [
			"3379792"
		]
	},
	"同飞股份_2021-11-01下午4_55_44_-同飞股份-300990": {
		"tags": [],
		"system": []
	},
	"爱康科技_2021-11-01下午4_59_31_-爱康科技-002610": {
		"tags": [],
		"system": []
	},
	"森特股份_2021-11-01下午5_19_14_-森特股份-603098": {
		"system": [
			"3379792",
			"0335063"
		],
		"tradeInfo": []
	},
	"中天科技_2021-11-01下午5_20_49_-中天科技-600522": {
		"tradeInfoText": [],
		"tags": [],
		"system": [
			"3379792"
		]
	},
	"undefined_2021-11-01下午5_53_42_-undefined-undefined": {
		"tags": [],
		"system": []
	},
	"undefined_2021-11-01下午5_54_08_-undefined-undefined": {
		"tags": [],
		"system": []
	},
	"undefined_2021-11-01下午5_54_12_-undefined-undefined": {
		"tags": [],
		"system": []
	},
	"undefined_2021-11-01下午5_54_15_-undefined-undefined": {
		"tags": [],
		"system": []
	},
	"undefined_2021-11-01下午5_54_19_-undefined-undefined": {
		"tags": [],
		"system": []
	},
	"undefined_2021-11-01下午5_54_38_-undefined-undefined": {
		"tags": [],
		"system": []
	},
	"undefined_2021-11-01下午6_01_43_-undefined-undefined": {
		"tags": [],
		"system": []
	},
	"undefined_2021-11-01下午6_01_54_-undefined-undefined": {
		"tags": [],
		"system": []
	},
	"undefined_2021-11-01下午6_02_00_-undefined-undefined": {
		"tags": [],
		"system": []
	},
	"undefined_2021-11-01下午6_02_05_-undefined-undefined": {
		"tags": [],
		"system": []
	},
	"士兰微_2021-11-01下午6_05_33_-士兰微-600460": {
		"tags": [],
		"system": []
	},
	"中船应急_2021-11-02下午5_04_56_-中船应急-300527": {
		"tags": [],
		"system": []
	},
	"吉鑫科技_2021-11-02下午5_05_39_-吉鑫科技-601218": {
		"tradeInfoText": [],
		"tags": [],
		"system": [
			"3379792"
		]
	},
	"凤凰光学_2021-11-02下午5_06_24_-凤凰光学-600071": {
		"tradeInfoText": [],
		"tags": [],
		"system": [
			"3379792"
		]
	},
	"中天科技_2021-11-02下午5_09_50_-中天科技-600522": {
		"tradeInfoText": [],
		"tags": [],
		"system": [
			"3379792"
		]
	},
	"清水源_2021-11-02下午5_19_07_-清水源-300437": {
		"system": [
			"3379792",
			"8415531",
			"2673493"
		],
		"tradeInfo": []
	},
	"联创股份_2021-11-02下午5_19_10_-联创股份-300343": {
		"system": [
			"3379792",
			"8415531",
			"2673493",
			"id_1722170897004_67020"
		],
		"tradeInfo": []
	},
	"沧州明珠_2021-11-02下午5_19_17_-沧州明珠-002108": {
		"tradeInfoText": [],
		"tags": [],
		"system": [
			"3379792"
		]
	},
	"湖北宜化_2021-11-02下午5_19_32_-湖北宜化-000422": {
		"system": [
			"3379792",
			"8415531",
			"id_1722170897004_67020",
			"id_1743912644162_63267"
		],
		"tradeInfo": []
	},
	"延安必康_2021-11-02下午5_19_45_-延安必康-002411": {
		"tradeInfoText": [],
		"tags": [],
		"system": [
			"6704841",
			"3379792"
		]
	},
	"兴发集团_2021-11-02下午5_20_02_-兴发集团-600141": {
		"tradeInfoText": [],
		"tags": [],
		"system": [
			"3379792"
		]
	},
	"上机数控_2021-11-02下午5_20_21_-上机数控-603185": {
		"tradeInfoText": [],
		"tags": [],
		"system": []
	},
	"金开新能_2021-11-02下午5_20_36_-金开新能-600821": {
		"tradeInfoText": [],
		"tags": [],
		"system": [
			"3379792"
		]
	},
	"石大胜华_2021-11-02下午5_23_06_-石大胜华-603026": {
		"system": [
			"3379792",
			"6704841",
			"id_1743912644162_63267"
		],
		"tradeInfo": []
	},
	"丰元股份_2021-11-02下午5_25_05_-丰元股份-002805": {
		"tradeInfoText": [],
		"tags": [],
		"system": [
			"3379792"
		]
	},
	"伊戈尔_2021-11-02下午5_25_13_-伊戈尔-002922": {
		"tradeInfoText": [],
		"tags": [],
		"system": [
			"3379792"
		]
	},
	"节能风电_2021-11-02下午5_25_17_-节能风电-601016": {
		"tags": [],
		"system": []
	},
	"云天化_2021-11-02下午5_25_32_-云天化-600096": {
		"tradeInfoText": [],
		"tags": [],
		"system": [
			"3379792"
		]
	},
	"天下秀_2021-11-02下午5_25_39_-天下秀-600556": {
		"tags": [],
		"system": []
	},
	"文山电力_2021-11-02下午5_27_05_-文山电力-600995": {
		"tradeInfoText": [],
		"tags": [],
		"system": [
			"3379792",
			"1266517"
		]
	},
	"创业黑马_2021-11-02下午5_27_08_-创业黑马-300688": {
		"tradeInfoText": [],
		"tags": [],
		"system": [
			"3379792"
		]
	},
	"爱康科技_2021-11-02下午5_27_14_-爱康科技-002610": {
		"system": [
			"3379792",
			"8415531",
			"2673493"
		],
		"tradeInfo": []
	},
	"英维克_2021-11-02下午5_28_57_-英维克-002837": {
		"tradeInfoText": [],
		"tags": [],
		"system": [
			"3379792"
		]
	},
	"中青宝_2021-11-02下午5_29_06_-中青宝-300052": {
		"system": [
			"3379792",
			"8415531",
			"2673493"
		],
		"tradeInfo": []
	},
	"大金重工_2021-11-02下午5_29_13_-大金重工-002487": {
		"system": [
			"3379792",
			"8415531",
			"2673493",
			"id_1722170897004_67020",
			"id_1743912644162_63267"
		],
		"tradeInfo": []
	},
	"同力日升_2021-11-02下午5_29_41_-同力日升-605286": {
		"system": [
			"3379792",
			"8415531",
			"2673493",
			"id_1743909850559_65502"
		],
		"tradeInfo": []
	},
	"undefined_2021-11-02下午5_30_04_-undefined-undefined": {
		"tags": [],
		"system": []
	},
	"undefined_2021-11-02下午5_30_11_-undefined-undefined": {
		"tags": [],
		"system": []
	},
	"undefined_2021-11-02下午5_30_18_-undefined-undefined": {
		"tags": [],
		"system": []
	},
	"undefined_2021-11-02下午5_30_25_-undefined-undefined": {
		"tags": [],
		"system": []
	},
	"undefined_2021-11-02下午5_30_31_-undefined-undefined": {
		"tags": [],
		"system": []
	},
	"undefined_2021-11-02下午5_30_36_-undefined-undefined": {
		"tags": [],
		"system": []
	},
	"undefined_2021-11-02下午5_30_39_-undefined-undefined": {
		"tags": [],
		"system": []
	},
	"undefined_2021-11-02下午5_31_05_-undefined-undefined": {
		"tags": [],
		"system": []
	},
	"undefined_2021-11-03下午3_00_16_-undefined-undefined": {
		"tags": [],
		"system": []
	},
	"中银绒业_2021-11-03下午7_44_23_-中银绒业-000982": {
		"tags": [],
		"system": []
	},
	"吉鑫科技_2021-11-03下午7_44_33_-吉鑫科技-601218": {
		"tradeInfoText": [],
		"tags": [],
		"system": [
			"3379792"
		]
	},
	"中天科技_2021-11-03下午7_44_36_-中天科技-600522": {
		"tradeInfoText": [],
		"tags": [],
		"system": [
			"3379792"
		]
	},
	"中船应急_2021-11-03下午7_44_40_-中船应急-300527": {
		"tags": [],
		"system": []
	},
	"佳创视讯_2021-11-03下午7_48_34_-佳创视讯-300264": {
		"tags": [],
		"system": []
	},
	"山西焦煤_2021-11-03下午7_53_34_-山西焦煤-000983": {
		"tradeInfoText": [],
		"tags": [],
		"system": [
			"3379792"
		]
	},
	"禾望电气_2021-11-03下午7_53_59_-禾望电气-603063": {
		"tags": [],
		"system": []
	},
	"科华数据_2021-11-03下午7_54_04_-科华数据-002335": {
		"tradeInfoText": [],
		"tags": [],
		"system": [
			"3379792"
		]
	},
	"新希望_2021-11-03下午7_54_19_-新希望-000876": {
		"tags": [],
		"system": []
	},
	"海源复材_2021-11-03下午7_54_30_-海源复材-002529": {
		"tradeInfoText": [],
		"tags": [],
		"system": [
			"3379792"
		]
	},
	"天下秀_2021-11-03下午7_54_49_-天下秀-600556": {
		"tags": [],
		"system": []
	},
	"创业黑马_2021-11-03下午7_57_24_-创业黑马-300688": {
		"tradeInfoText": [],
		"tags": [],
		"system": [
			"3379792"
		]
	},
	"清水源_2021-11-03下午7_57_29_-清水源-300437": {
		"system": [
			"3379792",
			"8415531",
			"2673493"
		],
		"tradeInfo": []
	},
	"宝通科技_2021-11-03下午7_58_37_-宝通科技-300031": {
		"tradeInfoText": [],
		"tags": [],
		"system": [
			"3379792"
		]
	},
	"石大胜华_2021-11-03下午7_58_56_-石大胜华-603026": {
		"system": [
			"3379792",
			"6704841",
			"id_1743912644162_63267"
		],
		"tradeInfo": []
	},
	"同力日升_2021-11-03下午8_05_03_-同力日升-605286": {
		"system": [
			"3379792",
			"8415531",
			"2673493",
			"id_1743909850559_65502"
		],
		"tradeInfo": []
	},
	"隆基股份_2021-11-03下午8_05_30_-隆基股份-601012": {
		"system": [
			"3379792",
			"7458589"
		],
		"tradeInfo": []
	},
	"兴发集团_2021-11-03下午8_05_58_-兴发集团-600141": {
		"tradeInfoText": [],
		"tags": [],
		"system": [
			"3379792"
		]
	},
	"云天化_2021-11-03下午8_09_20_-云天化-600096": {
		"system": [
			"3379792",
			"id_1743912644162_63267"
		],
		"tradeInfo": []
	},
	"大金重工_2021-11-03下午8_09_29_-大金重工-002487": {
		"system": [
			"3379792",
			"8415531",
			"2673493",
			"id_1743912644162_63267"
		],
		"tradeInfo": []
	},
	"爱康科技_2021-11-03下午8_09_58_-爱康科技-002610": {
		"system": [
			"3379792",
			"8415531",
			"2673493"
		],
		"tradeInfo": []
	},
	"湖北宜化_2021-11-03下午8_10_28_-湖北宜化-000422": {
		"system": [
			"3379792",
			"8415531",
			"id_1743912644162_63267"
		],
		"tradeInfo": []
	},
	"中青宝_2021-11-03下午8_11_57_-中青宝-300052": {
		"system": [
			"3379792",
			"8415531",
			"2673493"
		],
		"tradeInfo": []
	},
	"凤凰光学_2021-11-03下午8_14_46_-凤凰光学-600071": {
		"system": [
			"3379792",
			"id_1743909118220_54533"
		],
		"tradeInfo": []
	},
	"undefined_2021-11-03下午8_23_13_-undefined-undefined": {
		"tags": [],
		"system": []
	},
	"undefined_2021-11-03下午8_23_16_-undefined-undefined": {
		"tags": [],
		"system": []
	},
	"undefined_2021-11-03下午8_25_22_-undefined-undefined": {
		"tags": [],
		"system": []
	},
	"undefined_2021-11-03下午8_25_31_-undefined-undefined": {
		"tags": [],
		"system": []
	},
	"佳创视讯_2021-11-04下午5_16_44_-佳创视讯-300264": {
		"tradeInfoText": [],
		"tags": [],
		"system": [
			"3379792"
		]
	},
	"双一科技_2021-11-04下午5_16_48_-双一科技-300690": {
		"tags": [],
		"system": []
	},
	"恒帅股份_2021-11-04下午5_17_06_-恒帅股份-300969": {
		"tradeInfoText": [],
		"tags": [],
		"system": [
			"3589400",
			"3379792"
		]
	},
	"清水源_2021-11-04下午5_17_16_-清水源-300437": {
		"system": [
			"3379792",
			"8415531",
			"2673493",
			"id_1722170897004_67020"
		],
		"tradeInfo": []
	},
	"中青宝_2021-11-04下午5_17_21_-中青宝-300052": {
		"system": [
			"3379792",
			"8415531",
			"2673493",
			"id_1722170897004_67020"
		],
		"tradeInfo": []
	},
	"金雷股份_2021-11-04下午5_17_55_-金雷股份-300443": {
		"tradeInfoText": [],
		"tags": [],
		"system": [
			"3379792"
		]
	},
	"新强联_2021-11-04下午5_17_59_-新强联-300850": {
		"tags": [],
		"system": []
	},
	"当升科技_2021-11-04下午5_18_07_-当升科技-300073": {
		"tags": [],
		"system": []
	},
	"中天科技_2021-11-04下午5_19_07_-中天科技-600522": {
		"tradeInfoText": [],
		"tags": [],
		"system": [
			"3379792"
		]
	},
	"吉鑫科技_2021-11-04下午5_19_15_-吉鑫科技-601218": {
		"tradeInfoText": [],
		"tags": [],
		"system": [
			"3379792"
		]
	},
	"明阳智能_2021-11-04下午5_19_43_-明阳智能-601615": {
		"tradeInfoText": [
			[
				"10:04:38",
				"买入",
				"300",
				"34.600"
			]
		],
		"tags": [],
		"system": [
			"3379792"
		]
	},
	"天顺风能_2021-11-04下午5_19_50_-天顺风能-002531": {
		"tradeInfoText": [],
		"tags": [],
		"system": [
			"3379792"
		]
	},
	"恒润股份_2021-11-04下午5_20_19_-恒润股份-603985": {
		"tradeInfoText": [],
		"tags": [],
		"system": [
			"3379792"
		]
	},
	"大金重工_2021-11-04下午5_20_27_-大金重工-002487": {
		"system": [
			"3379792",
			"8415531",
			"2673493",
			"id_1722170897004_67020",
			"id_1743912644162_63267"
		],
		"tradeInfo": []
	},
	"金风科技_2021-11-04下午5_20_34_-金风科技-002202": {
		"tags": [],
		"system": []
	},
	"凤凰光学_2021-11-04下午5_20_49_-凤凰光学-600071": {
		"system": [
			"3379792",
			"0541013",
			"id_1743837737514_60701",
			"id_1743909118220_54533"
		],
		"tradeInfo": []
	},
	"内蒙华电_2021-11-04下午5_21_09_-内蒙华电-600863": {
		"tags": [],
		"system": []
	},
	"天下秀_2021-11-04下午5_21_13_-天下秀-600556": {
		"tradeInfoText": [],
		"tags": [],
		"system": [
			"3379792"
		]
	},
	"丰元股份_2021-11-04下午5_21_33_-丰元股份-002805": {
		"tradeInfoText": [],
		"tags": [],
		"system": [
			"3379792"
		]
	},
	"海源复材_2021-11-04下午5_21_51_-海源复材-002529": {
		"system": [
			"3379792",
			"id_1743912644162_63267"
		],
		"tradeInfo": []
	},
	"松芝股份_2021-11-04下午5_22_13_-松芝股份-002454": {
		"tags": [],
		"system": []
	},
	"东方电缆_2021-11-04下午5_22_32_-东方电缆-603606": {
		"system": [
			"3379792"
		],
		"tradeInfo": []
	},
	"中航重机_2021-11-04下午5_22_51_-中航重机-600765": {
		"tradeInfoText": [],
		"tags": [],
		"system": []
	},
	"比亚迪_2021-11-04下午5_23_56_-比亚迪-002594": {
		"tradeInfoText": [],
		"tags": [],
		"system": [
			"7458589",
			"6704841",
			"3379792"
		]
	},
	"永太科技_2021-11-04下午5_24_12_-永太科技-002326": {
		"system": [
			"3379792",
			"6704841",
			"id_1743912644162_63267"
		],
		"tradeInfo": []
	},
	"联创股份_2021-11-04下午5_25_12_-联创股份-300343": {
		"system": [
			"3379792",
			"8415531",
			"6704841",
			"0335063",
			"2673493",
			"id_1743912644162_63267"
		],
		"tradeInfo": []
	},
	"科华数据_2021-11-04下午5_30_18_-科华数据-002335": {
		"tradeInfoText": [],
		"tags": [],
		"system": [
			"3379792"
		]
	},
	"undefined_2021-11-04下午5_31_05_-undefined-undefined": {
		"tags": [],
		"system": []
	},
	"undefined_2021-11-04下午5_31_08_-undefined-undefined": {
		"tags": [],
		"system": []
	},
	"undefined_2021-11-04下午5_31_16_-undefined-undefined": {
		"tags": [],
		"system": []
	},
	"undefined_2021-11-04下午5_31_28_-undefined-undefined": {
		"tags": [],
		"system": []
	},
	"undefined_2021-11-04下午5_31_39_-undefined-undefined": {
		"tags": [],
		"system": []
	},
	"undefined_2021-11-04下午5_31_50_-undefined-undefined": {
		"tags": [],
		"system": []
	},
	"undefined_2021-11-04下午5_32_13_-undefined-undefined": {
		"tags": [],
		"system": []
	},
	"undefined_2021-11-04下午5_32_37_-undefined-undefined": {
		"tags": [],
		"system": []
	},
	"undefined_2021-11-04下午5_32_49_-undefined-undefined": {
		"tags": [],
		"system": []
	},
	"中科海讯_2021-11-04下午8_46_25_-中科海讯-300810": {
		"tags": [],
		"system": []
	},
	"佳创视讯_2021-11-05下午7_23_19_-佳创视讯-300264": {
		"tradeInfoText": [],
		"tags": [],
		"system": [
			"3379792"
		]
	},
	"清水源_2021-11-05下午7_23_35_-清水源-300437": {
		"system": [
			"3379792",
			"8415531",
			"2673493"
		],
		"tradeInfo": []
	},
	"创业黑马_2021-11-05下午7_23_49_-创业黑马-300688": {
		"tradeInfoText": [],
		"tags": [],
		"system": [
			"3379792"
		]
	},
	"创意信息_2021-11-05下午7_24_02_-创意信息-300366": {
		"tags": [],
		"system": []
	},
	"宝色股份_2021-11-05下午7_24_27_-宝色股份-300402": {
		"tradeInfoText": [],
		"tags": [],
		"system": [
			"3379792"
		]
	},
	"国光电器_2021-11-05下午7_24_56_-国光电器-002045": {
		"tags": [],
		"system": []
	},
	"易尚展示_2021-11-05下午7_25_06_-易尚展示-002751": {
		"tradeInfoText": [],
		"tags": [],
		"system": [
			"3379792"
		]
	},
	"凯撒文化_2021-11-05下午7_25_17_-凯撒文化-002425": {
		"tags": [],
		"system": []
	},
	"大金重工_2021-11-05下午7_25_27_-大金重工-002487": {
		"system": [
			"3379792",
			"8415531",
			"2673493",
			"id_1722170897004_67020",
			"id_1743912644162_63267"
		],
		"tradeInfo": []
	},
	"德昌股份_2021-11-05下午7_25_49_-德昌股份-605555": {
		"tags": [],
		"system": []
	},
	"汤姆猫_2021-11-05下午7_27_17_-汤姆猫-300459": {
		"tags": [],
		"system": []
	},
	"欣锐科技_2021-11-05下午7_27_42_-欣锐科技-300745": {
		"tags": [],
		"system": []
	},
	"景嘉微_2021-11-05下午7_27_49_-景嘉微-300474": {
		"tags": [],
		"system": []
	},
	"东山精密_2021-11-05下午7_28_03_-东山精密-002384": {
		"tags": [],
		"system": []
	},
	"恒润股份_2021-11-05下午7_28_11_-恒润股份-603985": {
		"tradeInfoText": [],
		"tags": [],
		"system": [
			"3379792"
		]
	},
	"水晶光电_2021-11-05下午7_28_46_-水晶光电-002273": {
		"tags": [],
		"system": []
	},
	"长信科技_2021-11-05下午7_29_14_-长信科技-300088": {
		"tags": [],
		"system": []
	},
	"新元科技_2021-11-05下午7_29_38_-新元科技-300472": {
		"tags": [],
		"system": []
	},
	"盛弘股份_2021-11-05下午7_29_46_-盛弘股份-300693": {
		"tags": [],
		"system": []
	},
	"高澜股份_2021-11-05下午7_29_53_-高澜股份-300499": {
		"tradeInfoText": [],
		"tags": [],
		"system": []
	},
	"爱康科技_2021-11-05下午7_29_55_-爱康科技-002610": {
		"system": [
			"3379792",
			"8415531",
			"2673493"
		],
		"tradeInfo": []
	},
	"湖北宜化_2021-11-05下午7_30_26_-湖北宜化-000422": {
		"system": [
			"3379792",
			"8415531",
			"0335063",
			"id_1743912644162_63267"
		],
		"tradeInfo": []
	},
	"丰元股份_2021-11-05下午7_30_30_-丰元股份-002805": {
		"tradeInfoText": [],
		"tags": [],
		"system": [
			"3379792"
		]
	},
	"英维克_2021-11-05下午7_30_52_-英维克-002837": {
		"tradeInfoText": [],
		"tags": [],
		"system": [
			"3379792"
		]
	},
	"云天化_2021-11-05下午7_31_17_-云天化-600096": {
		"tradeInfoText": [],
		"tags": [],
		"system": [
			"3379792"
		]
	},
	"禾望电气_2021-11-05下午7_31_25_-禾望电气-603063": {
		"tags": [],
		"system": []
	},
	"联创股份_2021-11-05下午7_31_35_-联创股份-300343": {
		"system": [
			"3379792",
			"8415531",
			"2673493",
			"id_1743912644162_63267"
		],
		"tradeInfo": []
	},
	"内蒙华电_2021-11-05下午7_31_54_-内蒙华电-600863": {
		"tags": [],
		"system": []
	},
	"伊戈尔_2021-11-05下午7_33_10_-伊戈尔-002922": {
		"tradeInfoText": [],
		"tags": [],
		"system": [
			"3379792"
		]
	},
	"松芝股份_2021-11-05下午7_33_50_-松芝股份-002454": {
		"tags": [],
		"system": []
	},
	"沧州明珠_2021-11-05下午7_34_11_-沧州明珠-002108": {
		"tradeInfoText": [],
		"tags": [],
		"system": [
			"3379792"
		]
	},
	"八一钢铁_2021-11-05下午7_35_51_-八一钢铁-600581": {
		"tags": [],
		"system": []
	},
	"石大胜华_2021-11-05下午7_36_05_-石大胜华-603026": {
		"system": [
			"3379792",
			"6704841",
			"id_1743912644162_63267"
		],
		"tradeInfo": []
	},
	"双一科技_2021-11-05下午7_41_44_-双一科技-300690": {
		"tags": [],
		"system": []
	},
	"金风科技_2021-11-05下午7_42_02_-金风科技-002202": {
		"tags": [],
		"system": []
	},
	"明阳智能_2021-11-05下午7_42_24_-明阳智能-601615": {
		"tradeInfoText": [
			[
				"09:33:12",
				"卖出",
				"300",
				"35.450"
			]
		],
		"tags": [],
		"system": [
			"3379792"
		]
	},
	"中青宝_2021-11-05下午7_43_13_-中青宝-300052": {
		"system": [
			"3379792",
			"8415531",
			"2673493"
		],
		"tradeInfo": []
	},
	"国科微_2021-11-05下午7_44_01_-国科微-300672": {
		"tags": [],
		"system": []
	},
	"吉鑫科技_2021-11-05下午7_44_05_-吉鑫科技-601218": {
		"tradeInfoText": [],
		"tags": [],
		"system": [
			"3379792"
		]
	},
	"华亚智能_2021-11-05下午7_44_12_-华亚智能-003043": {
		"tags": [],
		"system": []
	},
	"天下秀_2021-11-05下午7_44_15_-天下秀-600556": {
		"tradeInfoText": [],
		"tags": [],
		"system": [
			"3379792"
		]
	},
	"中天科技_2021-11-05下午7_44_22_-中天科技-600522": {
		"tradeInfoText": [],
		"tags": [],
		"system": [
			"3379792"
		]
	},
	"undefined_2021-11-05下午8_33_13_-undefined-undefined": {
		"system": [
			"3379792",
			"8415531",
			"2673493",
			"6153206",
			"id_1722170897004_67020"
		],
		"tradeInfo": []
	},
	"undefined_2021-11-05下午8_33_25_-undefined-undefined": {
		"tags": [],
		"system": []
	},
	"undefined_2021-11-05下午8_33_34_-undefined-undefined": {
		"tags": [],
		"system": []
	},
	"undefined_2021-11-05下午8_33_41_-undefined-undefined": {
		"tags": [],
		"system": []
	},
	"undefined_2021-11-05下午8_33_46_-undefined-undefined": {
		"tags": [],
		"system": []
	},
	"undefined_2021-11-05下午8_38_14_-undefined-undefined": {
		"tags": [],
		"system": []
	},
	"undefined_2021-11-05下午8_38_20_-undefined-undefined": {
		"tags": [],
		"system": []
	},
	"undefined_2021-11-05下午8_38_27_-undefined-undefined": {
		"tags": [],
		"system": []
	},
	"undefined_2021-11-05下午8_38_32_-undefined-undefined": {
		"tags": [],
		"system": []
	},
	"宝通科技_2021-11-08下午4_52_47_-宝通科技-300031": {
		"tradeInfoText": [],
		"tags": [],
		"system": [
			"3379792"
		]
	},
	"兴源环境_2021-11-08下午4_53_57_-兴源环境-300266": {
		"tags": [],
		"system": []
	},
	"天舟文化_2021-11-08下午4_54_04_-天舟文化-300148": {
		"tags": [],
		"system": []
	},
	"亿纬锂能_2021-11-08下午4_54_30_-亿纬锂能-300014": {
		"tags": [],
		"system": []
	},
	"国光电器_2021-11-08下午4_55_19_-国光电器-002045": {
		"tradeInfoText": [],
		"tags": [],
		"system": [
			"3379792"
		]
	},
	"同力日升_2021-11-08下午4_55_55_-同力日升-605286": {
		"tradeInfoText": [],
		"tags": [],
		"system": [
			"3379792"
		]
	},
	"天齐锂业_2021-11-08下午4_56_18_-天齐锂业-002466": {
		"tags": [],
		"system": []
	},
	"璞泰来_2021-11-08下午4_56_29_-璞泰来-603659": {
		"tags": [],
		"system": []
	},
	"石大胜华_2021-11-08下午4_56_31_-石大胜华-603026": {
		"tradeInfoText": [],
		"tags": [],
		"system": [
			"3379792"
		]
	},
	"金辰股份_2021-11-08下午4_56_57_-金辰股份-603396": {
		"tags": [],
		"system": []
	},
	"永太科技_2021-11-08下午4_57_06_-永太科技-002326": {
		"system": [
			"3379792",
			"6704841",
			"id_1743912644162_63267"
		],
		"tradeInfo": []
	},
	"易尚展示_2021-11-08下午4_57_11_-易尚展示-002751": {
		"tradeInfoText": [],
		"tags": [],
		"system": [
			"3379792"
		]
	},
	"科达制造_2021-11-08下午4_57_25_-科达制造-600499": {
		"tradeInfoText": [],
		"tags": [],
		"system": []
	},
	"华友钴业_2021-11-08下午4_58_02_-华友钴业-603799": {
		"tradeInfoText": [],
		"tags": [],
		"system": []
	},
	"吉鑫科技_2021-11-08下午5_01_18_-吉鑫科技-601218": {
		"tradeInfoText": [],
		"tags": [],
		"system": [
			"3379792"
		]
	},
	"创业黑马_2021-11-08下午5_02_07_-创业黑马-300688": {
		"tradeInfoText": [],
		"tags": [],
		"system": [
			"3379792"
		]
	},
	"中青宝_2021-11-08下午5_02_38_-中青宝-300052": {
		"system": [
			"3379792",
			"8415531",
			"2673493"
		],
		"tradeInfo": []
	},
	"清水源_2021-11-08下午5_03_12_-清水源-300437": {
		"system": [
			"3379792",
			"8415531",
			"2673493"
		],
		"tradeInfo": []
	},
	"中天科技_2021-11-08下午5_04_09_-中天科技-600522": {
		"tradeInfoText": [],
		"tags": [],
		"system": [
			"3379792"
		]
	},
	"佳创视讯_2021-11-08下午5_04_16_-佳创视讯-300264": {
		"tradeInfoText": [],
		"tags": [],
		"system": [
			"3379792"
		]
	},
	"凤凰光学_2021-11-08下午5_04_25_-凤凰光学-600071": {
		"tradeInfoText": [],
		"tags": [],
		"system": [
			"3379792"
		]
	},
	"undefined_2021-11-08下午5_04_57_-undefined-undefined": {
		"tags": [],
		"system": []
	},
	"undefined_2021-11-08下午5_05_00_-undefined-undefined": {
		"tradeInfoText": [],
		"tags": [],
		"system": [
			"3379792",
			"6153206"
		]
	},
	"undefined_2021-11-08下午5_05_11_-undefined-undefined": {
		"tags": [],
		"system": []
	},
	"undefined_2021-11-08下午5_06_05_-undefined-undefined": {
		"tags": [],
		"system": []
	},
	"undefined_2021-11-08下午5_06_21_-undefined-undefined": {
		"tags": [],
		"system": []
	},
	"水晶光电_2021-11-08下午7_41_34_-水晶光电-002273": {
		"tags": [],
		"system": []
	},
	"创意信息_2021-11-08下午7_48_44_-创意信息-300366": {
		"tags": [],
		"system": []
	},
	"丰元股份_2021-11-08下午7_49_22_-丰元股份-002805": {
		"tradeInfoText": [],
		"tags": [],
		"system": [
			"3379792"
		]
	},
	"凯撒文化_2021-11-08下午8_01_16_-凯撒文化-002425": {
		"tags": [],
		"system": []
	},
	"景嘉微_2021-11-09下午5_48_31_-景嘉微-300474": {
		"tags": [],
		"system": []
	},
	"拓新药业_2021-11-09下午5_48_54_-拓新药业-301089": {
		"tradeInfoText": [],
		"tags": [],
		"system": [
			"3379792"
		]
	},
	"海兰信_2021-11-09下午5_49_36_-海兰信-300065": {
		"tags": [],
		"system": []
	},
	"联创股份_2021-11-09下午5_49_55_-联创股份-300343": {
		"system": [
			"3379792",
			"8415531",
			"2673493",
			"id_1743912644162_63267"
		],
		"tradeInfo": []
	},
	"亿利洁能_2021-11-09下午5_50_17_-亿利洁能-600277": {
		"tags": [],
		"system": []
	},
	"华银电力_2021-11-09下午5_50_40_-华银电力-600744": {
		"tags": [],
		"system": []
	},
	"宁波精达_2021-11-09下午5_50_54_-宁波精达-603088": {
		"tradeInfoText": [],
		"tags": [],
		"system": [
			"3379792"
		]
	},
	"隆平高科_2021-11-09下午5_51_16_-隆平高科-000998": {
		"tags": [],
		"system": []
	},
	"晶科科技_2021-11-09下午5_51_32_-晶科科技-601778": {
		"tags": [],
		"system": []
	},
	"石大胜华_2021-11-09下午6_08_25_-石大胜华-603026": {
		"system": [
			"3379792",
			"6704841",
			"id_1743912644162_63267"
		],
		"tradeInfo": []
	},
	"卫士通_2021-11-09下午6_08_37_-卫士通-002268": {
		"tradeInfoText": [],
		"tags": [],
		"system": [
			"3379792"
		]
	},
	"露笑科技_2021-11-09下午6_08_41_-露笑科技-002617": {
		"tradeInfoText": [],
		"tags": [],
		"system": []
	},
	"森特股份_2021-11-09下午6_08_52_-森特股份-603098": {
		"tradeInfoText": [],
		"tags": [],
		"system": [
			"3379792"
		]
	},
	"湖北宜化_2021-11-09下午6_09_04_-湖北宜化-000422": {
		"tags": [
			"8425583"
		],
		"system": [
			"3379792",
			"8415531",
			"id_1719328919073_94772",
			"id_1722170897004_67020"
		],
		"tradeInfo": []
	},
	"金圆股份_2021-11-09下午6_09_17_-金圆股份-000546": {
		"tradeInfoText": [],
		"tags": [],
		"system": [
			"3379792"
		]
	},
	"中青宝_2021-11-09下午6_22_53_-中青宝-300052": {
		"system": [
			"3379792",
			"8415531",
			"2673493"
		],
		"tradeInfo": []
	},
	"易尚展示_2021-11-09下午6_24_40_-易尚展示-002751": {
		"tradeInfoText": [],
		"tags": [],
		"system": [
			"3379792"
		]
	},
	"天舟文化_2021-11-09下午6_25_08_-天舟文化-300148": {
		"tags": [],
		"system": []
	},
	"创意信息_2021-11-09下午6_25_58_-创意信息-300366": {
		"tags": [],
		"system": []
	},
	"兴源环境_2021-11-09下午6_39_06_-兴源环境-300266": {
		"tags": [],
		"system": []
	},
	"大金重工_2021-11-09下午6_42_25_-大金重工-002487": {
		"system": [
			"3379792",
			"8415531",
			"2673493",
			"id_1743912644162_63267"
		],
		"tradeInfo": []
	},
	"金开新能_2021-11-09下午6_43_55_-金开新能-600821": {
		"tradeInfoText": [],
		"tags": [],
		"system": [
			"3379792"
		]
	},
	"吉鑫科技_2021-11-09下午6_44_11_-吉鑫科技-601218": {
		"tradeInfoText": [],
		"tags": [],
		"system": [
			"3379792"
		]
	},
	"中天科技_2021-11-09下午6_44_14_-中天科技-600522": {
		"tradeInfoText": [],
		"tags": [],
		"system": [
			"3379792"
		]
	},
	"佳创视讯_2021-11-09下午6_44_26_-佳创视讯-300264": {
		"tradeInfoText": [],
		"tags": [],
		"system": [
			"3379792"
		]
	},
	"清水源_2021-11-09下午6_44_52_-清水源-300437": {
		"system": [
			"3379792",
			"8415531",
			"2673493"
		],
		"tradeInfo": []
	},
	"正泰电器_2021-11-09下午6_46_21_-正泰电器-601877": {
		"tags": [],
		"system": []
	},
	"国光电器_2021-11-09下午6_46_51_-国光电器-002045": {
		"tradeInfoText": [],
		"tags": [],
		"system": [
			"3379792"
		]
	},
	"天齐锂业_2021-11-09下午6_47_10_-天齐锂业-002466": {
		"tags": [],
		"system": []
	},
	"科华数据_2021-11-09下午6_47_56_-科华数据-002335": {
		"tradeInfoText": [],
		"tags": [],
		"system": [
			"3379792"
		]
	},
	"永太科技_2021-11-09下午6_48_08_-永太科技-002326": {
		"system": [
			"3379792",
			"6704841",
			"id_1743912644162_63267"
		],
		"tradeInfo": []
	},
	"undefined_2021-11-09下午6_49_17_-undefined-undefined": {
		"tags": [],
		"system": []
	},
	"undefined_2021-11-09下午6_49_22_-undefined-undefined": {
		"tags": [],
		"system": []
	},
	"undefined_2021-11-09下午6_49_30_-undefined-undefined": {
		"tags": [],
		"system": []
	},
	"undefined_2021-11-09下午6_49_41_-undefined-undefined": {
		"tags": [],
		"system": []
	},
	"undefined_2021-11-09下午6_49_53_-undefined-undefined": {
		"tags": [],
		"system": []
	},
	"undefined_2021-11-09下午6_50_35_-undefined-undefined": {
		"tags": [],
		"system": []
	},
	"undefined_2021-11-09下午6_51_19_-undefined-undefined": {
		"tags": [],
		"system": []
	},
	"清水源_2021-11-10下午4_41_59_-清水源-300437": {
		"tags": [
			"id_1746369575844_2703"
		],
		"system": [
			"3379792",
			"8415531",
			"2673493"
		],
		"tradeInfo": []
	},
	"拓新药业_2021-11-10下午4_58_07_-拓新药业-301089": {
		"system": [
			"3379792",
			"8415531",
			"2673493"
		],
		"tradeInfo": []
	},
	"宝色股份_2021-11-10下午4_58_29_-宝色股份-300402": {
		"tradeInfoText": [],
		"tags": [],
		"system": [
			"3379792"
		]
	},
	"中文在线_2021-11-10下午4_58_45_-中文在线-300364": {
		"tradeInfoText": [],
		"tags": [],
		"system": [
			"3379792"
		]
	},
	"平治信息_2021-11-10下午4_58_53_-平治信息-300571": {
		"tags": [],
		"system": []
	},
	"沃森生物_2021-11-10下午4_59_27_-沃森生物-300142": {
		"tags": [],
		"system": []
	},
	"长信科技_2021-11-10下午4_59_35_-长信科技-300088": {
		"tradeInfoText": [],
		"tags": [],
		"system": [
			"3379792"
		]
	},
	"金圆股份_2021-11-10下午4_59_54_-金圆股份-000546": {
		"tradeInfoText": [],
		"tags": [],
		"system": [
			"3379792"
		]
	},
	"易尚展示_2021-11-10下午5_00_15_-易尚展示-002751": {
		"tradeInfoText": [],
		"tags": [],
		"system": [
			"3379792"
		]
	},
	"宁波精达_2021-11-10下午5_00_49_-宁波精达-603088": {
		"tradeInfoText": [],
		"tags": [],
		"system": [
			"3379792"
		]
	},
	"创意信息_2021-11-10下午5_01_02_-创意信息-300366": {
		"tags": [],
		"system": []
	},
	"华银电力_2021-11-10下午5_01_20_-华银电力-600744": {
		"tags": [],
		"system": []
	},
	"东方日升_2021-11-10下午5_01_28_-东方日升-300118": {
		"tags": [],
		"system": []
	},
	"文山电力_2021-11-10下午5_02_01_-文山电力-600995": {
		"tradeInfoText": [],
		"tags": [],
		"system": [
			"3379792"
		]
	},
	"伊戈尔_2021-11-10下午5_02_33_-伊戈尔-002922": {
		"tradeInfoText": [],
		"tags": [],
		"system": [
			"3379792"
		]
	},
	"龙蟠科技_2021-11-10下午5_03_53_-龙蟠科技-603906": {
		"tradeInfoText": [],
		"tags": [],
		"system": [
			"6704841",
			"3379792"
		]
	},
	"多氟多_2021-11-10下午5_04_07_-多氟多-002407": {
		"tradeInfoText": [],
		"tags": [],
		"system": [
			"7458589"
		]
	},
	"金开新能_2021-11-10下午5_04_18_-金开新能-600821": {
		"tradeInfoText": [],
		"tags": [],
		"system": [
			"3379792"
		]
	},
	"大烨智能_2021-11-10下午5_04_28_-大烨智能-300670": {
		"tags": [],
		"system": []
	},
	"天齐锂业_2021-11-10下午5_04_33_-天齐锂业-002466": {
		"tags": [],
		"system": []
	},
	"景嘉微_2021-11-10下午5_05_08_-景嘉微-300474": {
		"tags": [],
		"system": []
	},
	"晶科科技_2021-11-10下午5_08_08_-晶科科技-601778": {
		"tags": [],
		"system": []
	},
	"宝通科技_2021-11-10下午5_08_52_-宝通科技-300031": {
		"tradeInfoText": [],
		"tags": [],
		"system": [
			"3379792"
		]
	},
	"佳创视讯_2021-11-10下午5_09_45_-佳创视讯-300264": {
		"tradeInfoText": [],
		"tags": [],
		"system": [
			"3379792"
		]
	},
	"大金重工_2021-11-10下午5_09_52_-大金重工-002487": {
		"system": [
			"3379792",
			"8415531",
			"2673493",
			"id_1722170897004_67020"
		],
		"tradeInfo": []
	},
	"隆平高科_2021-11-10下午5_10_56_-隆平高科-000998": {
		"tags": [],
		"system": []
	},
	"海兰信_2021-11-10下午5_11_23_-海兰信-300065": {
		"tags": [],
		"system": []
	},
	"中青宝_2021-11-10下午5_11_27_-中青宝-300052": {
		"system": [
			"3379792",
			"8415531",
			"2673493"
		],
		"tradeInfo": []
	},
	"天下秀_2021-11-10下午5_11_34_-天下秀-600556": {
		"tradeInfoText": [],
		"tags": [],
		"system": [
			"3379792"
		]
	},
	"天神娱乐_2021-11-10下午5_11_45_-天神娱乐-002354": {
		"tags": [],
		"system": []
	},
	"湖北宜化_2021-11-10下午5_11_50_-湖北宜化-000422": {
		"system": [
			"3379792",
			"8415531",
			"6704841",
			"id_1743912644162_63267"
		],
		"tradeInfo": []
	},
	"科华数据_2021-11-10下午5_12_02_-科华数据-002335": {
		"tradeInfoText": [],
		"tags": [],
		"system": [
			"3379792"
		]
	},
	"undefined_2021-11-10下午5_12_27_-undefined-undefined": {
		"system": [
			"3379792",
			"2673493"
		],
		"tradeInfo": []
	},
	"undefined_2021-11-10下午5_12_36_-undefined-undefined": {
		"tags": [],
		"system": []
	},
	"undefined_2021-11-10下午5_12_44_-undefined-undefined": {
		"tags": [],
		"system": []
	},
	"undefined_2021-11-10下午5_12_50_-undefined-undefined": {
		"tags": [],
		"system": []
	},
	"undefined_2021-11-10下午5_12_53_-undefined-undefined": {
		"tags": [],
		"system": []
	},
	"undefined_2021-11-10下午5_14_39_-undefined-undefined": {
		"tags": [],
		"system": []
	},
	"undefined_2021-11-10下午5_14_52_-undefined-undefined": {
		"tags": [],
		"system": []
	},
	"亿利洁能_2021-11-10下午5_18_47_-亿利洁能-600277": {
		"tags": [],
		"system": []
	},
	"卫士通_2021-11-10下午5_19_34_-卫士通-002268": {
		"tradeInfoText": [],
		"tags": [],
		"system": [
			"3379792"
		]
	},
	"宁波方正_2021-11-11下午5_32_57_-宁波方正-300998": {
		"tradeInfoText": [],
		"tags": [],
		"system": [
			"3379792"
		]
	},
	"中来股份_2021-11-11下午5_33_30_-中来股份-300393": {
		"tradeInfoText": [
			[
				"09:46:07",
				"买入",
				"700",
				"19.500"
			]
		],
		"tags": [],
		"system": [
			"3379792"
		]
	},
	"恒信东方_2021-11-11下午5_33_36_-恒信东方-300081": {
		"tradeInfoText": [],
		"tags": [
			"2055992"
		],
		"system": [
			"3379792"
		]
	},
	"争光股份_2021-11-11下午5_33_48_-争光股份-301092": {
		"tags": [],
		"system": []
	},
	"中文在线_2021-11-11下午5_34_24_-中文在线-300364": {
		"tradeInfoText": [],
		"tags": [],
		"system": [
			"3379792"
		]
	},
	"佳创视讯_2021-11-11下午5_34_32_-佳创视讯-300264": {
		"tradeInfoText": [],
		"tags": [],
		"system": [
			"3379792"
		]
	},
	"拓新药业_2021-11-11下午5_34_35_-拓新药业-301089": {
		"system": [
			"3379792",
			"8415531",
			"2673493"
		],
		"tradeInfo": []
	},
	"国科微_2021-11-11下午5_34_58_-国科微-300672": {
		"tradeInfoText": [],
		"tags": [],
		"system": [
			"3379792"
		]
	},
	"上声电子_2021-11-11下午5_35_34_-上声电子-688533": {
		"tradeInfoText": [],
		"tags": [],
		"system": [
			"3379792"
		]
	},
	"中青宝_2021-11-11下午5_35_43_-中青宝-300052": {
		"system": [
			"3379792",
			"8415531",
			"2673493"
		],
		"tradeInfo": []
	},
	"金圆股份_2021-11-11下午5_48_39_-金圆股份-000546": {
		"tradeInfoText": [],
		"tags": [],
		"system": [
			"3379792"
		]
	},
	"沪光股份_2021-11-11下午5_49_43_-沪光股份-605333": {
		"tradeInfoText": [],
		"tags": [],
		"system": [
			"3379792"
		]
	},
	"钧达股份_2021-11-11下午5_50_00_-钧达股份-002865": {
		"tradeInfoText": [],
		"tags": [],
		"system": [
			"8415531",
			"3379792"
		]
	},
	"北方华创_2021-11-11下午5_50_40_-北方华创-002371": {
		"tradeInfoText": [],
		"tags": [],
		"system": [
			"3379792"
		]
	},
	"湖北宜化_2021-11-11下午5_51_35_-湖北宜化-000422": {
		"system": [
			"3379792",
			"8415531",
			"0335063",
			"2673493",
			"id_1743912644162_63267"
		],
		"tradeInfo": []
	},
	"中兵红箭_2021-11-11下午5_51_50_-中兵红箭-000519": {
		"system": [
			"3379792",
			"6704841"
		],
		"tradeInfo": []
	},
	"黄河旋风_2021-11-11下午5_54_06_-黄河旋风-600172": {
		"tags": [],
		"system": []
	},
	"清水源_2021-11-11下午6_10_56_-清水源-300437": {
		"system": [
			"3379792",
			"8415531",
			"2673493"
		],
		"tradeInfo": []
	},
	"隆华科技_2021-11-11下午6_11_19_-隆华科技-300263": {
		"tags": [],
		"system": []
	},
	"长川科技_2021-11-11下午6_12_27_-长川科技-300604": {
		"tags": [],
		"system": []
	},
	"大金重工_2021-11-11下午6_14_29_-大金重工-002487": {
		"system": [
			"3379792",
			"8415531",
			"2673493"
		],
		"tradeInfo": []
	},
	"沃森生物_2021-11-11下午6_16_56_-沃森生物-300142": {
		"tags": [],
		"system": []
	},
	"宝色股份_2021-11-11下午6_17_36_-宝色股份-300402": {
		"tradeInfoText": [],
		"tags": [],
		"system": [
			"3379792"
		]
	},
	"东方日升_2021-11-11下午6_20_21_-东方日升-300118": {
		"tags": [],
		"system": []
	},
	"景嘉微_2021-11-11下午6_20_30_-景嘉微-300474": {
		"tags": [],
		"system": []
	},
	"湖北宜化_2021-11-11下午6_20_57_-湖北宜化-000422": {
		"tags": [],
		"system": []
	},
	"undefined_2021-11-11下午7_27_08_-undefined-undefined": {
		"tags": [],
		"system": []
	},
	"undefined_2021-11-11下午7_27_10_-undefined-undefined": {
		"tradeInfoText": [],
		"tags": [],
		"system": [
			"3379792"
		]
	},
	"undefined_2021-11-11下午7_27_33_-undefined-undefined": {
		"tags": [],
		"system": []
	},
	"undefined_2021-11-11下午7_27_37_-undefined-undefined": {
		"tags": [],
		"system": []
	},
	"undefined_2021-11-11下午7_29_56_-undefined-undefined": {
		"tags": [],
		"system": []
	},
	"undefined_2021-11-11下午7_30_03_-undefined-undefined": {
		"tags": [],
		"system": []
	},
	"undefined_2021-11-11下午7_30_09_-undefined-undefined": {
		"tags": [],
		"system": []
	},
	"undefined_2021-11-11下午10_51_21_-undefined-undefined": {
		"tradeInfoText": [],
		"tags": [],
		"system": [
			"3379792"
		]
	},
	"南岭民爆_2021-11-12下午4_39_12_-南岭民爆-002096": {
		"tags": [],
		"system": []
	},
	"佳创视讯_2021-11-12下午4_39_23_-佳创视讯-300264": {
		"tradeInfoText": [],
		"tags": [],
		"system": [
			"3379792"
		]
	},
	"清水源_2021-11-12下午4_39_41_-清水源-300437": {
		"system": [
			"3379792",
			"8415531",
			"2673493"
		],
		"tradeInfo": []
	},
	"隆华科技_2021-11-12下午4_41_40_-隆华科技-300263": {
		"tags": [],
		"system": []
	},
	"拓新药业_2021-11-12下午4_42_32_-拓新药业-301089": {
		"system": [
			"3379792",
			"8415531",
			"2673493"
		],
		"tradeInfo": []
	},
	"严牌股份_2021-11-12下午4_47_52_-严牌股份-301081": {
		"tags": [],
		"system": []
	},
	"易事特_2021-11-12下午4_48_14_-易事特-300376": {
		"tags": [],
		"system": []
	},
	"东方电热_2021-11-12下午4_48_30_-东方电热-300217": {
		"tags": [],
		"system": []
	},
	"恒信东方_2021-11-12下午4_48_54_-恒信东方-300081": {
		"tradeInfoText": [],
		"tags": [
			"2055992"
		],
		"system": [
			"3379792"
		]
	},
	"中来股份_2021-11-12下午4_49_20_-中来股份-300393": {
		"tradeInfoText": [
			[
				"09:30:26",
				"卖出",
				"700",
				"20.090"
			]
		],
		"tags": [],
		"system": [
			"3379792"
		]
	},
	"鹏辉能源_2021-11-12下午4_49_30_-鹏辉能源-300438": {
		"tradeInfoText": [],
		"tags": [],
		"system": [
			"3379792"
		]
	},
	"中文在线_2021-11-12下午4_49_46_-中文在线-300364": {
		"tradeInfoText": [],
		"tags": [],
		"system": [
			"3379792"
		]
	},
	"宁波方正_2021-11-12下午4_49_53_-宁波方正-300998": {
		"tradeInfoText": [],
		"tags": [],
		"system": [
			"3379792"
		]
	},
	"中利集团_2021-11-12下午4_50_06_-中利集团-002309": {
		"tradeInfoText": [],
		"tags": [],
		"system": [
			"3379792"
		]
	},
	"强瑞技术_2021-11-12下午4_50_23_-强瑞技术-301128": {
		"tags": [],
		"system": []
	},
	"天通股份_2021-11-12下午4_51_18_-天通股份-600330": {
		"tradeInfoText": [],
		"tags": [],
		"system": [
			"3379792"
		]
	},
	"沪光股份_2021-11-12下午4_51_37_-沪光股份-605333": {
		"tradeInfoText": [],
		"tags": [],
		"system": [
			"3379792"
		]
	},
	"爱旭股份_2021-11-12下午4_52_05_-爱旭股份-600732": {
		"tradeInfoText": [],
		"tags": [],
		"system": [
			"3379792",
			"8415531"
		]
	},
	"卫士通_2021-11-12下午4_52_24_-卫士通-002268": {
		"tradeInfoText": [],
		"tags": [],
		"system": [
			"3379792"
		]
	},
	"德昌股份_2021-11-12下午4_52_28_-德昌股份-605555": {
		"tags": [],
		"system": []
	},
	"四方股份_2021-11-12下午4_52_53_-四方股份-601126": {
		"tradeInfoText": [],
		"tags": [],
		"system": [
			"3379792"
		]
	},
	"中天科技_2021-11-12下午4_52_57_-中天科技-600522": {
		"tradeInfoText": [],
		"tags": [],
		"system": [
			"3379792"
		]
	},
	"广宇发展_2021-11-12下午4_53_34_-广宇发展-000537": {
		"tradeInfoText": [],
		"tags": [],
		"system": [
			"3379792"
		]
	},
	"海兰信_2021-11-12下午4_54_07_-海兰信-300065": {
		"tradeInfoText": [],
		"tags": [],
		"system": [
			"3379792"
		]
	},
	"国轩高科_2021-11-12下午4_54_34_-国轩高科-002074": {
		"tags": [],
		"system": []
	},
	"undefined_2021-11-12下午4_55_47_-undefined-undefined": {
		"tags": [],
		"system": []
	},
	"undefined_2021-11-12下午4_55_51_-undefined-undefined": {
		"tags": [],
		"system": []
	},
	"undefined_2021-11-12下午4_55_55_-undefined-undefined": {
		"tags": [],
		"system": []
	},
	"undefined_2021-11-12下午4_55_57_-undefined-undefined": {
		"tags": [],
		"system": []
	},
	"undefined_2021-11-12下午4_56_01_-undefined-undefined": {
		"tags": [],
		"system": []
	},
	"undefined_2021-11-12下午4_56_03_-undefined-undefined": {
		"tags": [],
		"system": []
	},
	"undefined_2021-11-12下午4_56_19_-undefined-undefined": {
		"tags": [],
		"system": []
	},
	"undefined_2021-11-12下午4_56_32_-undefined-undefined": {
		"tags": [],
		"system": []
	},
	"undefined_2021-11-12下午4_56_37_-undefined-undefined": {
		"tags": [],
		"system": []
	},
	"undefined_2021-11-12下午4_56_51_-undefined-undefined": {
		"tags": [],
		"system": []
	},
	"金圆股份_2021-11-12下午5_07_15_-金圆股份-000546": {
		"tags": [],
		"system": []
	},
	"沪电股份_2021-11-12下午10_20_21_-沪电股份-002463": {
		"tags": [],
		"system": []
	},
	"新元科技_2021-11-15下午7_36_05_-新元科技-300472": {
		"tags": [],
		"system": []
	},
	"创业黑马_2021-11-15下午7_36_08_-创业黑马-300688": {
		"tradeInfoText": [],
		"tags": [],
		"system": [
			"3379792"
		]
	},
	"黄河旋风_2021-11-15下午7_36_47_-黄河旋风-600172": {
		"tags": [],
		"system": []
	},
	"湖北宜化_2021-11-15下午7_37_08_-湖北宜化-000422": {
		"system": [
			"3379792",
			"8415531",
			"6704841",
			"id_1722170897004_67020",
			"id_1743912644162_63267"
		],
		"tradeInfo": []
	},
	"宁波精达_2021-11-15下午7_37_37_-宁波精达-603088": {
		"tradeInfoText": [],
		"tags": [],
		"system": [
			"3379792"
		]
	},
	"永太科技_2021-11-15下午7_37_56_-永太科技-002326": {
		"tags": [
			"8425583"
		],
		"system": [
			"3379792",
			"8415531",
			"0335063",
			"id_1743912644162_63267"
		],
		"tradeInfo": []
	},
	"隆平高科_2021-11-15下午7_38_58_-隆平高科-000998": {
		"tags": [],
		"system": []
	},
	"吉鑫科技_2021-11-15下午7_39_11_-吉鑫科技-601218": {
		"tradeInfoText": [],
		"tags": [],
		"system": [
			"3379792"
		]
	},
	"中文在线_2021-11-15下午7_40_01_-中文在线-300364": {
		"tradeInfoText": [],
		"tags": [],
		"system": [
			"3379792"
		]
	},
	"南岭民爆_2021-11-15下午7_40_06_-南岭民爆-002096": {
		"tradeInfoText": [],
		"tags": [],
		"system": [
			"3379792"
		]
	},
	"景嘉微_2021-11-15下午7_40_47_-景嘉微-300474": {
		"tags": [],
		"system": []
	},
	"联创股份_2021-11-15下午7_41_58_-联创股份-300343": {
		"system": [
			"3379792",
			"6704841",
			"id_1743912644162_63267"
		],
		"tradeInfo": []
	},
	"中天科技_2021-11-15下午7_43_12_-中天科技-600522": {
		"tradeInfoText": [],
		"tags": [],
		"system": [
			"3379792"
		]
	},
	"争光股份_2021-11-15下午7_43_28_-争光股份-301092": {
		"tags": [],
		"system": []
	},
	"智光电气_2021-11-15下午7_44_56_-智光电气-002169": {
		"tags": [],
		"system": []
	},
	"严牌股份_2021-11-15下午8_04_05_-严牌股份-301081": {
		"tags": [],
		"system": []
	},
	"宁波方正_2021-11-15下午8_04_09_-宁波方正-300998": {
		"tradeInfoText": [],
		"tags": [],
		"system": [
			"3379792"
		]
	},
	"思特奇_2021-11-15下午8_04_20_-思特奇-300608": {
		"tags": [],
		"system": []
	},
	"丝路视觉_2021-11-15下午8_04_27_-丝路视觉-300556": {
		"tags": [],
		"system": []
	},
	"百胜智能_2021-11-15下午8_04_29_-百胜智能-301083": {
		"tags": [],
		"system": []
	},
	"C金埔_2021-11-15下午8_04_38_-C金埔-301098": {
		"tags": [],
		"system": []
	},
	"四维图新_2021-11-15下午8_05_25_-四维图新-002405": {
		"tags": [],
		"system": []
	},
	"四方股份_2021-11-15下午8_05_47_-四方股份-601126": {
		"tradeInfoText": [],
		"tags": [],
		"system": [
			"3379792"
		]
	},
	"沪光股份_2021-11-15下午8_06_02_-沪光股份-605333": {
		"tradeInfoText": [],
		"tags": [],
		"system": [
			"3379792"
		]
	},
	"亚太科技_2021-11-15下午8_07_02_-亚太科技-002540": {
		"tags": [],
		"system": []
	},
	"北方华创_2021-11-15下午8_10_06_-北方华创-002371": {
		"tags": [],
		"system": []
	},
	"一汽富维_2021-11-15下午8_10_20_-一汽富维-600742": {
		"tags": [],
		"system": []
	},
	"东方电缆_2021-11-15下午8_11_34_-东方电缆-603606": {
		"tradeInfoText": [],
		"tags": [],
		"system": [
			"3379792"
		]
	},
	"中来股份_2021-11-15下午8_11_46_-中来股份-300393": {
		"tradeInfoText": [],
		"tags": [],
		"system": [
			"3379792"
		]
	},
	"清水源_2021-11-15下午8_11_55_-清水源-300437": {
		"system": [
			"3379792",
			"8415531",
			"2673493"
		],
		"tradeInfo": []
	},
	"东方电热_2021-11-15下午8_12_07_-东方电热-300217": {
		"tags": [],
		"system": []
	},
	"易事特_2021-11-15下午8_12_39_-易事特-300376": {
		"tags": [],
		"system": []
	},
	"宝通科技_2021-11-15下午8_12_43_-宝通科技-300031": {
		"tradeInfoText": [],
		"tags": [],
		"system": [
			"3379792"
		]
	},
	"C隆华_2021-11-15下午8_12_49_-C隆华-301149": {
		"tags": [],
		"system": []
	},
	"爱康科技_2021-11-15下午8_12_55_-爱康科技-002610": {
		"tradeInfoText": [],
		"tags": [],
		"system": [
			"3379792"
		]
	},
	"undefined_2021-11-15下午8_15_28_-undefined-undefined": {
		"tradeInfoText": [],
		"tags": [],
		"system": [
			"3379792"
		]
	},
	"undefined_2021-11-15下午8_17_45_-undefined-undefined": {
		"tags": [],
		"system": []
	},
	"undefined_2021-11-15下午8_17_55_-undefined-undefined": {
		"tags": [],
		"system": []
	},
	"undefined_2021-11-15下午8_18_01_-undefined-undefined": {
		"tags": [],
		"system": []
	},
	"undefined_2021-11-15下午8_18_06_-undefined-undefined": {
		"tags": [],
		"system": []
	},
	"undefined_2021-11-15下午8_18_11_-undefined-undefined": {
		"tags": [],
		"system": []
	},
	"undefined_2021-11-15下午8_18_18_-undefined-undefined": {
		"tags": [],
		"system": []
	},
	"undefined_2021-11-15下午8_18_23_-undefined-undefined": {
		"tags": [],
		"system": []
	},
	"undefined_2021-11-15下午8_19_07_-undefined-undefined": {
		"tags": [],
		"system": []
	},
	"undefined_2021-11-15下午8_19_10_-undefined-undefined": {
		"tags": [],
		"system": []
	},
	"undefined_2021-11-15下午8_19_20_-undefined-undefined": {
		"tags": [],
		"system": []
	},
	"恒信东方_2021-11-15下午10_00_20_-恒信东方-300081": {
		"tradeInfoText": [],
		"tags": [],
		"system": [
			"3379792"
		]
	},
	"盛天网络_2021-11-16下午3_37_00_-盛天网络-300494": {
		"tags": [],
		"system": []
	},
	"苏奥传感_2021-11-16下午3_37_21_-苏奥传感-300507": {
		"tags": [],
		"system": []
	},
	"一汽富维_2021-11-16下午3_37_51_-一汽富维-600742": {
		"tradeInfoText": [],
		"tags": [],
		"system": [
			"3379792"
		]
	},
	"大金重工_2021-11-16下午3_38_39_-大金重工-002487": {
		"system": [
			"3379792",
			"8415531",
			"2673493"
		],
		"tradeInfo": []
	},
	"恒润股份_2021-11-16下午3_38_43_-恒润股份-603985": {
		"tradeInfoText": [],
		"tags": [],
		"system": [
			"3379792"
		]
	},
	"东方电缆_2021-11-16下午3_38_49_-东方电缆-603606": {
		"tradeInfoText": [],
		"tags": [],
		"system": [
			"3379792"
		]
	},
	"京泉华_2021-11-16下午3_38_53_-京泉华-002885": {
		"tradeInfoText": [],
		"tags": [],
		"system": [
			"3379792"
		]
	},
	"日盈电子_2021-11-16下午3_39_40_-日盈电子-603286": {
		"tags": [],
		"system": []
	},
	"海南椰岛_2021-11-16下午3_39_47_-海南椰岛-600238": {
		"tags": [],
		"system": []
	},
	"宝鹰股份_2021-11-16下午3_40_27_-宝鹰股份-002047": {
		"tradeInfoText": [],
		"tags": [],
		"system": [
			"3379792"
		]
	},
	"佳创视讯_2021-11-16下午3_40_41_-佳创视讯-300264": {
		"tradeInfoText": [],
		"tags": [],
		"system": [
			"3379792"
		]
	},
	"翰宇药业_2021-11-16下午3_40_50_-翰宇药业-300199": {
		"tradeInfoText": [],
		"tags": [],
		"system": [
			"3379792"
		]
	},
	"中天科技_2021-11-16下午3_41_02_-中天科技-600522": {
		"tradeInfoText": [],
		"tags": [],
		"system": [
			"3379792"
		]
	},
	"C强瑞_2021-11-16下午4_50_44_-C强瑞-301128": {
		"tags": [],
		"system": []
	},
	"多瑞医药_2021-11-16下午4_50_48_-多瑞医药-301075": {
		"tags": [],
		"system": []
	},
	"严牌股份_2021-11-16下午4_50_50_-严牌股份-301081": {
		"tags": [],
		"system": []
	},
	"争光股份_2021-11-16下午4_51_03_-争光股份-301092": {
		"tradeInfoText": [],
		"tags": [],
		"system": [
			"3379792"
		]
	},
	"C隆华_2021-11-16下午4_51_06_-C隆华-301149": {
		"tags": [],
		"system": []
	},
	"宁波方正_2021-11-16下午4_51_10_-宁波方正-300998": {
		"tradeInfoText": [],
		"tags": [],
		"system": [
			"3379792"
		]
	},
	"C力诺_2021-11-16下午4_51_14_-C力诺-301188": {
		"tags": [],
		"system": []
	},
	"湖北宜化_2021-11-16下午4_52_32_-湖北宜化-000422": {
		"system": [
			"3379792",
			"8415531",
			"6704841",
			"id_1743912644162_63267"
		],
		"tradeInfo": []
	},
	"中来股份_2021-11-16下午4_55_08_-中来股份-300393": {
		"tradeInfoText": [],
		"tags": [],
		"system": [
			"3379792"
		]
	},
	"思特奇_2021-11-16下午4_56_35_-思特奇-300608": {
		"tags": [],
		"system": []
	},
	"丝路视觉_2021-11-16下午4_58_10_-丝路视觉-300556": {
		"tags": [],
		"system": []
	},
	"中青宝_2021-11-16下午4_58_38_-中青宝-300052": {
		"system": [
			"3379792",
			"2673493"
		],
		"tradeInfo": []
	},
	"四维图新_2021-11-16下午4_58_50_-四维图新-002405": {
		"tags": [],
		"system": []
	},
	"沪光股份_2021-11-16下午4_59_05_-沪光股份-605333": {
		"tradeInfoText": [],
		"tags": [],
		"system": [
			"3379792"
		]
	},
	"四方股份_2021-11-16下午4_59_08_-四方股份-601126": {
		"tradeInfoText": [],
		"tags": [],
		"system": [
			"3379792"
		]
	},
	"爱康科技_2021-11-16下午4_59_16_-爱康科技-002610": {
		"tradeInfoText": [],
		"tags": [],
		"system": [
			"3379792"
		]
	},
	"恒信东方_2021-11-16下午4_59_21_-恒信东方-300081": {
		"tradeInfoText": [],
		"tags": [],
		"system": [
			"3379792"
		]
	},
	"雅本化学_2021-11-16下午4_59_25_-雅本化学-300261": {
		"tradeInfoText": [],
		"tags": [],
		"system": [
			"3379792"
		]
	},
	"新国脉_2021-11-16下午4_59_29_-新国脉-600640": {
		"tags": [],
		"system": []
	},
	"undefined_2021-11-16下午4_59_57_-undefined-undefined": {
		"tags": [],
		"system": []
	},
	"undefined_2021-11-16下午5_00_03_-undefined-undefined": {
		"tags": [],
		"system": []
	},
	"undefined_2021-11-16下午5_00_07_-undefined-undefined": {
		"tags": [],
		"system": []
	},
	"undefined_2021-11-16下午5_00_36_-undefined-undefined": {
		"tags": [],
		"system": []
	},
	"undefined_2021-11-16下午5_00_42_-undefined-undefined": {
		"tags": [],
		"system": []
	},
	"undefined_2021-11-16下午5_00_46_-undefined-undefined": {
		"tags": [],
		"system": []
	},
	"金银河_2021-11-17下午4_34_54_-金银河-300619": {
		"tradeInfoText": [],
		"tags": [],
		"system": [
			"3379792"
		]
	},
	"鹏辉能源_2021-11-17下午4_35_23_-鹏辉能源-300438": {
		"tradeInfoText": [],
		"tags": [],
		"system": [
			"3379792"
		]
	},
	"炬华科技_2021-11-17下午4_35_31_-炬华科技-300360": {
		"tags": [],
		"system": []
	},
	"中利集团_2021-11-17下午5_05_18_-中利集团-002309": {
		"tradeInfoText": [],
		"tags": [],
		"system": [
			"3379792"
		]
	},
	"爱康科技_2021-11-17下午5_05_26_-爱康科技-002610": {
		"tradeInfoText": [
			[
				"10:09:13",
				"买入",
				"1400",
				"6.120"
			]
		],
		"tags": [],
		"system": [
			"3379792"
		]
	},
	"横店东磁_2021-11-17下午5_08_09_-横店东磁-002056": {
		"tradeInfoText": [],
		"tags": [],
		"system": [
			"3379792"
		]
	},
	"西藏珠峰_2021-11-17下午5_28_23_-西藏珠峰-600338": {
		"tradeInfoText": [],
		"tags": [],
		"system": [
			"3379792"
		]
	},
	"永兴材料_2021-11-17下午5_29_04_-永兴材料-002756": {
		"tradeInfoText": [],
		"tags": [],
		"system": [
			"3379792"
		]
	},
	"天齐锂业_2021-11-17下午5_29_13_-天齐锂业-002466": {
		"tradeInfoText": [],
		"tags": [],
		"system": [
			"3379792"
		]
	},
	"东方电缆_2021-11-17下午5_29_29_-东方电缆-603606": {
		"tradeInfoText": [],
		"tags": [],
		"system": [
			"3379792"
		]
	},
	"振江股份_2021-11-17下午5_29_49_-振江股份-603507": {
		"tradeInfoText": [],
		"tags": [],
		"system": []
	},
	"大金重工_2021-11-17下午5_30_32_-大金重工-002487": {
		"tags": [
			"id_1746369575844_2703",
			"5227616"
		],
		"system": [
			"3379792",
			"8415531",
			"2673493",
			"id_1743912644162_63267"
		],
		"tradeInfo": []
	},
	"清水源_2021-11-17下午5_32_39_-清水源-300437": {
		"system": [
			"3379792",
			"8415531",
			"2673493"
		],
		"tradeInfo": []
	},
	"海兰信_2021-11-17下午5_32_44_-海兰信-300065": {
		"tradeInfoText": [],
		"tags": [],
		"system": [
			"3379792"
		]
	},
	"翰宇药业_2021-11-17下午5_33_29_-翰宇药业-300199": {
		"tradeInfoText": [],
		"tags": [],
		"system": [
			"3379792"
		]
	},
	"C金埔_2021-11-17下午5_33_42_-C金埔-301098": {
		"tags": [],
		"system": []
	},
	"恒信东方_2021-11-17下午5_33_47_-恒信东方-300081": {
		"tradeInfoText": [],
		"tags": [],
		"system": [
			"3379792"
		]
	},
	"盛天网络_2021-11-17下午5_33_52_-盛天网络-300494": {
		"tags": [],
		"system": []
	},
	"南岭民爆_2021-11-17下午5_34_14_-南岭民爆-002096": {
		"tradeInfoText": [],
		"tags": [],
		"system": [
			"3379792"
		]
	},
	"京泉华_2021-11-17下午5_34_20_-京泉华-002885": {
		"tradeInfoText": [],
		"tags": [],
		"system": [
			"3379792"
		]
	},
	"丝路视觉_2021-11-17下午5_34_30_-丝路视觉-300556": {
		"tags": [],
		"system": []
	},
	"沪光股份_2021-11-17下午5_35_18_-沪光股份-605333": {
		"tradeInfoText": [],
		"tags": [],
		"system": [
			"3379792"
		]
	},
	"天汽模_2021-11-17下午5_35_21_-天汽模-002510": {
		"tags": [],
		"system": []
	},
	"佳创视讯_2021-11-17下午5_36_35_-佳创视讯-300264": {
		"tradeInfoText": [],
		"tags": [],
		"system": [
			"3379792"
		]
	},
	"宝鹰股份_2021-11-17下午5_37_02_-宝鹰股份-002047": {
		"tradeInfoText": [],
		"tags": [],
		"system": [
			"3379792"
		]
	},
	"苏奥传感_2021-11-17下午5_38_58_-苏奥传感-300507": {
		"tags": [],
		"system": []
	},
	"宝通科技_2021-11-17下午5_39_04_-宝通科技-300031": {
		"tradeInfoText": [],
		"tags": [],
		"system": [
			"3379792"
		]
	},
	"四维图新_2021-11-17下午5_39_10_-四维图新-002405": {
		"tags": [],
		"system": []
	},
	"四方股份_2021-11-17下午5_39_18_-四方股份-601126": {
		"tradeInfoText": [],
		"tags": [],
		"system": [
			"3379792"
		]
	},
	"中天科技_2021-11-17下午5_39_49_-中天科技-600522": {
		"tradeInfoText": [],
		"tags": [],
		"system": [
			"3379792"
		]
	},
	"undefined_2021-11-17下午11_59_39_-undefined-undefined": {
		"tags": [],
		"system": []
	},
	"undefined_2021-11-17下午11_59_40_-undefined-undefined": {
		"tags": [],
		"system": []
	},
	"undefined_2021-11-17下午11_59_41_-undefined-undefined": {
		"tags": [],
		"system": []
	},
	"undefined_2021-11-17下午11_59_42_-undefined-undefined": {
		"tags": [],
		"system": []
	},
	"undefined_2021-11-17下午11_59_43_-undefined-undefined": {
		"tags": [],
		"system": []
	},
	"佳创视讯_2021-11-18下午11_47_09_-佳创视讯-300264": {
		"tradeInfoText": [],
		"tags": [],
		"system": [
			"3379792"
		]
	},
	"露笑科技_2021-11-18下午11_47_21_-露笑科技-002617": {
		"tags": [],
		"system": []
	},
	"炬华科技_2021-11-18下午11_47_26_-炬华科技-300360": {
		"tags": [],
		"system": []
	},
	"清水源_2021-11-18下午11_47_31_-清水源-300437": {
		"system": [
			"3379792",
			"2673493"
		],
		"tradeInfo": []
	},
	"盛天网络_2021-11-18下午11_47_46_-盛天网络-300494": {
		"tags": [],
		"system": []
	},
	"爱康科技_2021-11-18下午11_48_13_-爱康科技-002610": {
		"system": [
			"3379792",
			"8415531",
			"2673493"
		],
		"tradeInfo": [
			[
				"09:31:09",
				"卖出",
				"1400",
				"5.910"
			]
		]
	},
	"宝鹰股份_2021-11-18下午11_48_23_-宝鹰股份-002047": {
		"tradeInfoText": [],
		"tags": [],
		"system": [
			"3379792"
		]
	},
	"翰宇药业_2021-11-18下午11_48_35_-翰宇药业-300199": {
		"tradeInfoText": [],
		"tags": [],
		"system": [
			"3379792"
		]
	},
	"中青宝_2021-11-18下午11_48_43_-中青宝-300052": {
		"system": [
			"3379792",
			"8415531",
			"2673493"
		],
		"tradeInfo": []
	},
	"景嘉微_2021-11-18下午11_50_07_-景嘉微-300474": {
		"tags": [],
		"system": []
	},
	"裕兴股份_2021-11-18下午11_50_14_-裕兴股份-300305": {
		"tags": [],
		"system": []
	},
	"中捷精工_2021-11-18下午11_50_18_-中捷精工-301072": {
		"tradeInfoText": [],
		"tags": [],
		"system": [
			"3379792"
		]
	},
	"金银河_2021-11-18下午11_50_24_-金银河-300619": {
		"tradeInfoText": [],
		"tags": [],
		"system": [
			"3379792"
		]
	},
	"川网传媒_2021-11-18下午11_50_30_-川网传媒-300987": {
		"tags": [],
		"system": []
	},
	"天能重工_2021-11-18下午11_50_44_-天能重工-300569": {
		"tags": [],
		"system": []
	},
	"九安医疗_2021-11-18下午11_51_02_-九安医疗-002432": {
		"tradeInfoText": [],
		"tags": [],
		"system": [
			"3379792",
			"6734208",
			"8415531",
			"2673493"
		]
	},
	"天下秀_2021-11-18下午11_51_13_-天下秀-600556": {
		"tradeInfoText": [],
		"tags": [],
		"system": []
	},
	"川能动力_2021-11-18下午11_51_57_-川能动力-000155": {
		"tags": [],
		"system": []
	},
	"永兴材料_2021-11-18下午11_52_15_-永兴材料-002756": {
		"tradeInfoText": [],
		"tags": [],
		"system": [
			"3379792"
		]
	},
	"西藏珠峰_2021-11-18下午11_52_21_-西藏珠峰-600338": {
		"tradeInfoText": [],
		"tags": [],
		"system": [
			"3379792"
		]
	},
	"西藏矿业_2021-11-18下午11_52_32_-西藏矿业-000762": {
		"tradeInfoText": [],
		"tags": [],
		"system": [
			"3379792"
		]
	},
	"科达制造_2021-11-18下午11_52_37_-科达制造-600499": {
		"tradeInfoText": [],
		"tags": [],
		"system": [
			"3379792"
		]
	},
	"恒信东方_2021-11-18下午11_54_05_-恒信东方-300081": {
		"tradeInfoText": [],
		"tags": [],
		"system": [
			"3379792"
		]
	},
	"金圆股份_2021-11-18下午11_54_20_-金圆股份-000546": {
		"tradeInfoText": [],
		"tags": [],
		"system": [
			"3379792"
		]
	},
	"盐湖股份_2021-11-18下午11_54_35_-盐湖股份-000792": {
		"tags": [],
		"system": []
	},
	"江特电机_2021-11-18下午11_54_39_-江特电机-002176": {
		"system": [
			"3379792",
			"6704841",
			"id_1743912644162_63267"
		],
		"tradeInfo": []
	},
	"鹏辉能源_2021-11-18下午11_54_44_-鹏辉能源-300438": {
		"tradeInfoText": [],
		"tags": [],
		"system": [
			"3379792"
		]
	},
	"天齐锂业_2021-11-18下午11_55_43_-天齐锂业-002466": {
		"system": [
			"3379792",
			"6704841"
		],
		"tradeInfo": []
	},
	"大金重工_2021-11-18下午11_55_47_-大金重工-002487": {
		"tradeInfoText": [],
		"tags": [],
		"system": [
			"3379792",
			"8415531"
		]
	},
	"东方电缆_2021-11-18下午11_56_24_-东方电缆-603606": {
		"tradeInfoText": [],
		"tags": [],
		"system": [
			"3379792"
		]
	},
	"undefined_2021-11-18下午11_57_57_-undefined-undefined": {
		"tags": [],
		"system": []
	},
	"undefined_2021-11-18下午11_58_04_-undefined-undefined": {
		"tags": [],
		"system": []
	},
	"undefined_2021-11-18下午11_58_13_-undefined-undefined": {
		"tags": [],
		"system": []
	},
	"undefined_2021-11-18下午11_58_47_-undefined-undefined": {
		"tags": [],
		"system": []
	},
	"undefined_2021-11-18下午11_58_52_-undefined-undefined": {
		"tags": [],
		"system": []
	},
	"undefined_2021-11-18下午11_58_56_-undefined-undefined": {
		"tags": [],
		"system": []
	},
	"宝胜股份_2021-11-19上午12_00_59_-宝胜股份-600973": {
		"tags": [],
		"system": []
	},
	"全柴动力_2021-11-19上午12_12_21_-全柴动力-600218": {
		"tags": [],
		"system": []
	},
	"盾安环境_2021-11-19上午12_12_33_-盾安环境-002011": {
		"tradeInfoText": [],
		"tags": [],
		"system": [
			"3379792"
		]
	},
	"嵘泰股份_2021-11-19上午12_12_41_-嵘泰股份-605133": {
		"tradeInfoText": [],
		"tags": [],
		"system": [
			"3379792"
		]
	},
	"中泰股份_2021-11-19下午6_27_19_-中泰股份-300435": {
		"tradeInfoText": [],
		"tags": [],
		"system": []
	},
	"中捷精工_2021-11-19下午6_27_25_-中捷精工-301072": {
		"tradeInfoText": [],
		"tags": [],
		"system": [
			"3379792"
		]
	},
	"东方日升_2021-11-19下午6_27_34_-东方日升-300118": {
		"tradeInfoText": [],
		"tags": [],
		"system": [
			"3589400"
		]
	},
	"苏奥传感_2021-11-19下午6_28_08_-苏奥传感-300507": {
		"tags": [],
		"system": []
	},
	"厚普股份_2021-11-19下午6_28_32_-厚普股份-300471": {
		"tags": [],
		"system": []
	},
	"海兰信_2021-11-19下午6_28_47_-海兰信-300065": {
		"tradeInfoText": [],
		"tags": [],
		"system": [
			"3379792"
		]
	},
	"九安医疗_2021-11-19下午6_29_25_-九安医疗-002432": {
		"tradeInfoText": [],
		"tags": [],
		"system": [
			"3379792",
			"6734208",
			"8415531",
			"2673493",
			"7108001"
		]
	},
	"美锦能源_2021-11-19下午6_29_40_-美锦能源-000723": {
		"tags": [],
		"system": []
	},
	"浙江黎明_2021-11-19下午6_30_26_-浙江黎明-603048": {
		"tags": [],
		"system": []
	},
	"中利集团_2021-11-19下午6_30_29_-中利集团-002309": {
		"tradeInfoText": [
			[
				"15:00:00",
				"买入",
				"1000",
				"8.570"
			]
		],
		"tags": [],
		"system": [
			"3379792"
		]
	},
	"镇洋发展_2021-11-19下午6_31_10_-镇洋发展-603213": {
		"tradeInfoText": [],
		"tags": [],
		"system": [
			"3379792"
		]
	},
	"天下秀_2021-11-19下午6_32_01_-天下秀-600556": {
		"tradeInfoText": [],
		"tags": [],
		"system": []
	},
	"国光电器_2021-11-19下午6_32_20_-国光电器-002045": {
		"tradeInfoText": [
			[
				"09:34:47",
				"买入",
				"500",
				"15.090"
			],
			[
				"09:41:36",
				"买入",
				"500",
				"15.090"
			]
		],
		"tags": [],
		"system": [
			"3379792"
		]
	},
	"中来股份_2021-11-19下午6_33_27_-中来股份-300393": {
		"tradeInfoText": [],
		"tags": [],
		"system": [
			"3379792"
		]
	},
	"西藏珠峰_2021-11-19下午6_34_22_-西藏珠峰-600338": {
		"tradeInfoText": [],
		"tags": [],
		"system": [
			"3379792"
		]
	},
	"联创股份_2021-11-19下午6_34_28_-联创股份-300343": {
		"tradeInfoText": [],
		"tags": [],
		"system": [
			"3379792"
		]
	},
	"天润工业_2021-11-19下午6_36_12_-天润工业-002283": {
		"tags": [],
		"system": []
	},
	"鹏辉能源_2021-11-19下午6_37_38_-鹏辉能源-300438": {
		"tradeInfoText": [],
		"tags": [],
		"system": [
			"3379792"
		]
	},
	"宝胜股份_2021-11-19下午6_49_11_-宝胜股份-600973": {
		"tags": [],
		"system": []
	},
	"大金重工_2021-11-19下午6_58_43_-大金重工-002487": {
		"tradeInfoText": [],
		"tags": [],
		"system": [
			"3379792",
			"8415531"
		]
	},
	"景嘉微_2021-11-19下午7_02_04_-景嘉微-300474": {
		"tags": [],
		"system": []
	},
	"爱康科技_2021-11-19下午7_03_52_-爱康科技-002610": {
		"tradeInfoText": [],
		"tags": [],
		"system": [
			"3379792"
		]
	},
	"佳创视讯_2021-11-19下午7_04_36_-佳创视讯-300264": {
		"tradeInfoText": [],
		"tags": [],
		"system": [
			"3379792"
		]
	},
	"中银绒业_2021-11-19下午7_05_07_-中银绒业-000982": {
		"tradeInfoText": [],
		"tags": [],
		"system": [
			"3379792"
		]
	},
	"新洁能_2021-11-19下午7_05_20_-新洁能-605111": {
		"tradeInfoText": [],
		"tags": [],
		"system": [
			"3589400",
			"3379792"
		]
	},
	"金银河_2021-11-19下午7_05_29_-金银河-300619": {
		"tradeInfoText": [],
		"tags": [],
		"system": [
			"3379792"
		]
	},
	"歌尔股份_2021-11-19下午7_05_33_-歌尔股份-002241": {
		"tradeInfoText": [],
		"tags": [],
		"system": [
			"3589400"
		]
	},
	"undefined_2021-11-19下午9_33_29_-undefined-undefined": {
		"tags": [],
		"system": []
	},
	"undefined_2021-11-19下午9_33_33_-undefined-undefined": {
		"tags": [],
		"system": []
	},
	"undefined_2021-11-19下午9_34_07_-undefined-undefined": {
		"tradeInfoText": [],
		"tags": [],
		"system": [
			"6153206"
		]
	},
	"undefined_2021-11-19下午9_34_13_-undefined-undefined": {
		"tags": [],
		"system": []
	},
	"西藏矿业_2021-11-19下午9_35_38_-西藏矿业-000762": {
		"tradeInfoText": [],
		"tags": [],
		"system": [
			"3379792"
		]
	},
	"川能动力_2021-11-19下午9_35_44_-川能动力-000155": {
		"tradeInfoText": [],
		"tags": [],
		"system": [
			"3379792"
		]
	},
	"C万祥_2021-11-21下午7_38_04_-C万祥-301180": {
		"tags": [],
		"system": []
	},
	"扬杰科技_2021-11-22下午6_20_48_-扬杰科技-300373": {
		"tags": [],
		"system": []
	},
	"中文在线_2021-11-22下午6_21_01_-中文在线-300364": {
		"tradeInfoText": [],
		"tags": [],
		"system": [
			"3379792"
		]
	},
	"恒信东方_2021-11-22下午6_22_15_-恒信东方-300081": {
		"tradeInfoText": [],
		"tags": [],
		"system": [
			"3379792"
		]
	},
	"当升科技_2021-11-22下午6_22_30_-当升科技-300073": {
		"tags": [],
		"system": []
	},
	"一汽富维_2021-11-22下午6_22_45_-一汽富维-600742": {
		"tradeInfoText": [],
		"tags": [],
		"system": [
			"3379792"
		]
	},
	"九安医疗_2021-11-22下午6_22_48_-九安医疗-002432": {
		"tradeInfoText": [],
		"tags": [],
		"system": [
			"3379792",
			"6734208",
			"8415531",
			"2673493",
			"7108001"
		]
	},
	"天通股份_2021-11-22下午6_23_02_-天通股份-600330": {
		"tradeInfoText": [],
		"tags": [],
		"system": [
			"3379792"
		]
	},
	"科达制造_2021-11-22下午6_23_32_-科达制造-600499": {
		"tradeInfoText": [],
		"tags": [],
		"system": [
			"3379792"
		]
	},
	"镇洋发展_2021-11-22下午6_23_38_-镇洋发展-603213": {
		"tradeInfoText": [],
		"tags": [],
		"system": [
			"3379792"
		]
	},
	"拓邦股份_2021-11-22下午6_24_16_-拓邦股份-002139": {
		"tags": [],
		"system": []
	},
	"华阳集团_2021-11-22下午6_24_24_-华阳集团-002906": {
		"tags": [],
		"system": []
	},
	"华友钴业_2021-11-22下午6_24_54_-华友钴业-603799": {
		"tags": [],
		"system": []
	},
	"西藏城投_2021-11-22下午6_24_59_-西藏城投-600773": {
		"tradeInfoText": [],
		"tags": [],
		"system": [
			"3379792"
		]
	},
	"永太科技_2021-11-22下午6_25_39_-永太科技-002326": {
		"tradeInfoText": [],
		"tags": [],
		"system": [
			"3379792"
		]
	},
	"广宇发展_2021-11-22下午6_26_13_-广宇发展-000537": {
		"tradeInfoText": [],
		"tags": [],
		"system": [
			"3379792"
		]
	},
	"康盛股份_2021-11-22下午6_26_16_-康盛股份-002418": {
		"tradeInfoText": [],
		"tags": [],
		"system": [
			"3379792"
		]
	},
	"中泰股份_2021-11-22下午6_26_30_-中泰股份-300435": {
		"tags": [],
		"system": []
	},
	"嵘泰股份_2021-11-22下午6_26_38_-嵘泰股份-605133": {
		"tradeInfoText": [],
		"tags": [],
		"system": [
			"3379792"
		]
	},
	"沪电股份_2021-11-22下午6_26_57_-沪电股份-002463": {
		"tags": [],
		"system": []
	},
	"山东威达_2021-11-22下午6_27_36_-山东威达-002026": {
		"tradeInfoText": [],
		"tags": [],
		"system": [
			"3379792"
		]
	},
	"中来股份_2021-11-22下午6_27_54_-中来股份-300393": {
		"tradeInfoText": [],
		"tags": [],
		"system": [
			"3379792"
		]
	},
	"天下秀_2021-11-22下午6_27_56_-天下秀-600556": {
		"tradeInfoText": [],
		"tags": [],
		"system": []
	},
	"拓新药业_2021-11-22下午6_27_59_-拓新药业-301089": {
		"tradeInfoText": [],
		"tags": [],
		"system": [
			"3379792"
		]
	},
	"苏奥传感_2021-11-22下午6_28_04_-苏奥传感-300507": {
		"tags": [],
		"system": []
	},
	"中捷精工_2021-11-22下午6_28_23_-中捷精工-301072": {
		"tradeInfoText": [],
		"tags": [],
		"system": [
			"3379792"
		]
	},
	"金银河_2021-11-22下午6_28_30_-金银河-300619": {
		"tradeInfoText": [],
		"tags": [],
		"system": [
			"3379792"
		]
	},
	"中银绒业_2021-11-22下午6_28_55_-中银绒业-000982": {
		"tradeInfoText": [],
		"tags": [],
		"system": [
			"3379792"
		]
	},
	"海兰信_2021-11-22下午6_29_20_-海兰信-300065": {
		"tradeInfoText": [],
		"tags": [],
		"system": [
			"3379792"
		]
	},
	"大金重工_2021-11-22下午6_29_26_-大金重工-002487": {
		"tradeInfoText": [],
		"tags": [],
		"system": [
			"3379792",
			"8415531"
		]
	},
	"沪光股份_2021-11-22下午6_29_31_-沪光股份-605333": {
		"tradeInfoText": [],
		"tags": [],
		"system": [
			"3379792"
		]
	},
	"东方日升_2021-11-22下午6_29_40_-东方日升-300118": {
		"tradeInfoText": [
			[
				"14:39:13",
				"买入",
				"300",
				"37.090"
			]
		],
		"tags": [],
		"system": [
			"3589400"
		]
	},
	"西藏珠峰_2021-11-22下午6_29_45_-西藏珠峰-600338": {
		"tradeInfoText": [],
		"tags": [],
		"system": [
			"3379792"
		]
	},
	"中青宝_2021-11-22下午6_29_58_-中青宝-300052": {
		"tradeInfoText": [],
		"tags": [],
		"system": [
			"3379792"
		]
	},
	"新洁能_2021-11-22下午6_30_03_-新洁能-605111": {
		"tradeInfoText": [],
		"tags": [],
		"system": [
			"3589400",
			"3379792"
		]
	},
	"国科微_2021-11-22下午6_30_12_-国科微-300672": {
		"tradeInfoText": [],
		"tags": [],
		"system": [
			"3379792"
		]
	},
	"美锦能源_2021-11-22下午6_30_25_-美锦能源-000723": {
		"tags": [],
		"system": []
	},
	"宁德时代_2021-11-22下午6_30_27_-宁德时代-300750": {
		"tradeInfoText": [],
		"tags": [],
		"system": [
			"7458589",
			"3379792"
		]
	},
	"中利集团_2021-11-22下午6_30_33_-中利集团-002309": {
		"tradeInfoText": [
			[
				"09:25:00",
				"卖出",
				"1000",
				"8.470"
			]
		],
		"tags": [],
		"system": [
			"3379792"
		]
	},
	"undefined_2021-11-22下午6_30_55_-undefined-undefined": {
		"tags": [],
		"system": []
	},
	"undefined_2021-11-22下午6_30_58_-undefined-undefined": {
		"tags": [],
		"system": []
	},
	"undefined_2021-11-22下午6_31_13_-undefined-undefined": {
		"tags": [],
		"system": []
	},
	"undefined_2021-11-22下午6_31_17_-undefined-undefined": {
		"tags": [],
		"system": []
	},
	"undefined_2021-11-22下午6_31_44_-undefined-undefined": {
		"tags": [],
		"system": []
	},
	"N雅创_2021-11-23下午8_51_57_-N雅创-301099": {
		"tags": [],
		"system": []
	},
	"正海磁材_2021-11-23下午8_52_22_-正海磁材-300224": {
		"tradeInfoText": [
			[
				"09:33:50",
				"买入",
				"600",
				"16.850"
			]
		],
		"tags": [],
		"system": [
			"3379792"
		]
	},
	"上声电子_2021-11-23下午8_52_41_-上声电子-688533": {
		"tradeInfoText": [],
		"tags": [],
		"system": [
			"3379792"
		]
	},
	"中文在线_2021-11-23下午8_53_08_-中文在线-300364": {
		"tradeInfoText": [],
		"tags": [],
		"system": [
			"3379792"
		]
	},
	"海泰科_2021-11-23下午8_53_14_-海泰科-301022": {
		"tags": [],
		"system": []
	},
	"南都电源_2021-11-23下午8_53_21_-南都电源-300068": {
		"tags": [],
		"system": []
	},
	"九安医疗_2021-11-23下午8_54_02_-九安医疗-002432": {
		"tradeInfoText": [],
		"tags": [],
		"system": [
			"3379792",
			"6734208",
			"8415531",
			"2673493",
			"7108001"
		]
	},
	"鞍重股份_2021-11-23下午8_54_36_-鞍重股份-002667": {
		"tags": [],
		"system": []
	},
	"盛洋科技_2021-11-23下午8_54_48_-盛洋科技-603703": {
		"tags": [],
		"system": []
	},
	"盾安环境_2021-11-23下午8_55_07_-盾安环境-002011": {
		"tradeInfoText": [],
		"tags": [],
		"system": [
			"3379792"
		]
	},
	"亚星锚链_2021-11-23下午8_55_23_-亚星锚链-601890": {
		"tags": [],
		"system": []
	},
	"横店东磁_2021-11-23下午8_55_27_-横店东磁-002056": {
		"tradeInfoText": [],
		"tags": [],
		"system": [
			"3379792"
		]
	},
	"中银绒业_2021-11-23下午8_55_55_-中银绒业-000982": {
		"tradeInfoText": [],
		"tags": [],
		"system": [
			"3379792"
		]
	},
	"包钢股份_2021-11-23下午8_58_10_-包钢股份-600010": {
		"tags": [],
		"system": []
	},
	"运达股份_2021-11-23下午8_58_19_-运达股份-300772": {
		"tradeInfoText": [],
		"tags": [],
		"system": [
			"3379792"
		]
	},
	"晶澳科技_2021-11-23下午8_58_35_-晶澳科技-002459": {
		"tradeInfoText": [],
		"tags": [],
		"system": [
			"3379792"
		]
	},
	"大金重工_2021-11-23下午8_58_47_-大金重工-002487": {
		"tradeInfoText": [],
		"tags": [],
		"system": [
			"3379792",
			"8415531"
		]
	},
	"明阳智能_2021-11-23下午9_00_03_-明阳智能-601615": {
		"tradeInfoText": [],
		"tags": [],
		"system": [
			"3379792"
		]
	},
	"中来股份_2021-11-23下午9_00_30_-中来股份-300393": {
		"tradeInfoText": [],
		"tags": [],
		"system": [
			"3379792"
		]
	},
	"中泰股份_2021-11-23下午9_00_40_-中泰股份-300435": {
		"tags": [],
		"system": []
	},
	"恒信东方_2021-11-23下午9_02_28_-恒信东方-300081": {
		"tradeInfoText": [],
		"tags": [],
		"system": [
			"3379792"
		]
	},
	"苏奥传感_2021-11-23下午9_02_43_-苏奥传感-300507": {
		"tradeInfoText": [],
		"tags": [],
		"system": [
			"3379792"
		]
	},
	"永太科技_2021-11-23下午9_03_01_-永太科技-002326": {
		"tradeInfoText": [],
		"tags": [],
		"system": [
			"3379792"
		]
	},
	"爱康科技_2021-11-23下午9_03_20_-爱康科技-002610": {
		"tradeInfoText": [
			[
				"09:30:15",
				"卖出",
				"2400",
				"5.700"
			]
		],
		"tags": [],
		"system": [
			"3379792"
		]
	},
	"康盛股份_2021-11-23下午9_03_36_-康盛股份-002418": {
		"tradeInfoText": [],
		"tags": [],
		"system": [
			"3379792"
		]
	},
	"西藏珠峰_2021-11-23下午9_04_15_-西藏珠峰-600338": {
		"tradeInfoText": [],
		"tags": [],
		"system": [
			"3379792",
			"0751098"
		]
	},
	"东方日升_2021-11-23下午9_04_35_-东方日升-300118": {
		"tradeInfoText": [
			[
				"09:30:25",
				"卖出",
				"300",
				"37.050"
			]
		],
		"tags": [],
		"system": [
			"3589400"
		]
	},
	"中利集团_2021-11-23下午9_05_07_-中利集团-002309": {
		"tradeInfoText": [],
		"tags": [],
		"system": [
			"3379792"
		]
	},
	"美锦能源_2021-11-23下午9_05_16_-美锦能源-000723": {
		"tags": [],
		"system": []
	},
	"佳创视讯_2021-11-23下午9_05_23_-佳创视讯-300264": {
		"tradeInfoText": [],
		"tags": [],
		"system": [
			"3379792"
		]
	},
	"扬杰科技_2021-11-23下午9_05_27_-扬杰科技-300373": {
		"tags": [],
		"system": []
	},
	"许继电气_2021-11-23下午9_05_48_-许继电气-000400": {
		"tradeInfoText": [],
		"tags": [],
		"system": [
			"3379792"
		]
	},
	"中青宝_2021-11-23下午9_05_52_-中青宝-300052": {
		"tradeInfoText": [],
		"tags": [],
		"system": [
			"3379792"
		]
	},
	"金银河_2021-11-23下午9_05_56_-金银河-300619": {
		"tradeInfoText": [],
		"tags": [],
		"system": [
			"3379792"
		]
	},
	"科达制造_2021-11-23下午9_06_00_-科达制造-600499": {
		"tradeInfoText": [],
		"tags": [],
		"system": [
			"3379792"
		]
	},
	"京城股份_2021-11-23下午9_18_01_-京城股份-600860": {
		"tradeInfoText": [],
		"tags": [],
		"system": [
			"8415531",
			"3379792"
		]
	},
	"undefined_2021-11-23下午10_24_40_-undefined-undefined": {
		"tags": [],
		"system": []
	},
	"undefined_2021-11-23下午10_24_47_-undefined-undefined": {
		"tags": [],
		"system": []
	},
	"undefined_2021-11-23下午10_25_51_-undefined-undefined": {
		"tags": [],
		"system": []
	},
	"undefined_2021-11-23下午10_25_56_-undefined-undefined": {
		"tags": [],
		"system": []
	},
	"undefined_2021-11-23下午10_26_03_-undefined-undefined": {
		"tags": [],
		"system": []
	},
	"苏奥传感_2021-11-24下午8_46_01_-苏奥传感-300507": {
		"tradeInfoText": [],
		"tags": [],
		"system": [
			"3379792"
		]
	},
	"GQY视讯_2021-11-24下午8_47_40_-GQY视讯-300076": {
		"tags": [],
		"system": []
	},
	"佳创视讯_2021-11-24下午8_47_58_-佳创视讯-300264": {
		"tradeInfoText": [],
		"tags": [],
		"system": [
			"3379792"
		]
	},
	"中捷精工_2021-11-24下午8_48_14_-中捷精工-301072": {
		"tradeInfoText": [],
		"tags": [],
		"system": [
			"3379792"
		]
	},
	"正海磁材_2021-11-24下午8_48_30_-正海磁材-300224": {
		"tradeInfoText": [
			[
				"09:36:41",
				"卖出",
				"600",
				"17.720"
			]
		],
		"tags": [],
		"system": [
			"3379792",
			"8812495"
		]
	},
	"金运激光_2021-11-24下午8_48_43_-金运激光-300220": {
		"tags": [],
		"system": []
	},
	"大富科技_2021-11-24下午8_48_57_-大富科技-300134": {
		"tags": [],
		"system": []
	},
	"康平科技_2021-11-24下午8_49_12_-康平科技-300907": {
		"tags": [],
		"system": []
	},
	"翰宇药业_2021-11-24下午8_49_43_-翰宇药业-300199": {
		"tradeInfoText": [],
		"tags": [],
		"system": [
			"3379792"
		]
	},
	"银河磁体_2021-11-24下午8_50_05_-银河磁体-300127": {
		"tags": [],
		"system": []
	},
	"金力永磁_2021-11-24下午8_50_16_-金力永磁-300748": {
		"tags": [],
		"system": []
	},
	"九安医疗_2021-11-24下午8_50_37_-九安医疗-002432": {
		"tradeInfoText": [],
		"tags": [],
		"system": [
			"3379792",
			"6734208",
			"8415531",
			"2673493",
			"7108001"
		]
	},
	"沪光股份_2021-11-24下午8_50_40_-沪光股份-605333": {
		"tradeInfoText": [],
		"tags": [],
		"system": [
			"3379792"
		]
	},
	"海源复材_2021-11-24下午8_50_48_-海源复材-002529": {
		"tradeInfoText": [],
		"tags": [],
		"system": [
			"3379792"
		]
	},
	"镇洋发展_2021-11-24下午8_50_56_-镇洋发展-603213": {
		"tradeInfoText": [],
		"tags": [],
		"system": [
			"3379792"
		]
	},
	"浙江黎明_2021-11-24下午8_51_41_-浙江黎明-603048": {
		"tags": [],
		"system": []
	},
	"宝鹰股份_2021-11-24下午8_51_55_-宝鹰股份-002047": {
		"tradeInfoText": [],
		"tags": [],
		"system": [
			"3379792"
		]
	},
	"英洛华_2021-11-24下午8_51_59_-英洛华-000795": {
		"tradeInfoText": [],
		"tags": [],
		"system": [
			"3379792"
		]
	},
	"运达股份_2021-11-24下午8_55_43_-运达股份-300772": {
		"tradeInfoText": [],
		"tags": [],
		"system": [
			"3379792"
		]
	},
	"中银绒业_2021-11-24下午8_56_34_-中银绒业-000982": {
		"tradeInfoText": [],
		"tags": [],
		"system": [
			"3379792"
		]
	},
	"中文在线_2021-11-24下午8_57_11_-中文在线-300364": {
		"tradeInfoText": [],
		"tags": [],
		"system": [
			"3379792"
		]
	},
	"沪电股份_2021-11-24下午8_58_44_-沪电股份-002463": {
		"tradeInfoText": [],
		"tags": [],
		"system": [
			"3589400"
		]
	},
	"C雅创_2021-11-24下午8_58_50_-C雅创-301099": {
		"tags": [],
		"system": []
	},
	"科达制造_2021-11-24下午8_59_13_-科达制造-600499": {
		"tradeInfoText": [],
		"tags": [],
		"system": [
			"3379792"
		]
	},
	"恒信东方_2021-11-24下午8_59_19_-恒信东方-300081": {
		"tradeInfoText": [],
		"tags": [],
		"system": [
			"3379792"
		]
	},
	"新洁能_2021-11-24下午8_59_26_-新洁能-605111": {
		"tradeInfoText": [],
		"tags": [],
		"system": [
			"3589400",
			"3379792"
		]
	},
	"金银河_2021-11-24下午8_59_37_-金银河-300619": {
		"tradeInfoText": [],
		"tags": [],
		"system": [
			"3379792"
		]
	},
	"宁波韵升_2021-11-24下午8_59_43_-宁波韵升-600366": {
		"tradeInfoText": [],
		"tags": [],
		"system": []
	},
	"扬杰科技_2021-11-24下午8_59_50_-扬杰科技-300373": {
		"tags": [],
		"system": []
	},
	"undefined_2021-11-24下午9_00_23_-undefined-undefined": {
		"tags": [],
		"system": []
	},
	"undefined_2021-11-24下午9_00_26_-undefined-undefined": {
		"tags": [],
		"system": []
	},
	"undefined_2021-11-24下午9_00_33_-undefined-undefined": {
		"tags": [],
		"system": []
	},
	"undefined_2021-11-24下午9_00_43_-undefined-undefined": {
		"tags": [],
		"system": []
	},
	"undefined_2021-11-24下午9_01_11_-undefined-undefined": {
		"tags": [],
		"system": []
	},
	"undefined_2021-11-24下午9_01_15_-undefined-undefined": {
		"tags": [],
		"system": []
	},
	"undefined_2021-11-24下午9_01_27_-undefined-undefined": {
		"tags": [],
		"system": []
	},
	"国科微_2021-11-25下午6_16_29_-国科微-300672": {
		"tradeInfoText": [],
		"tags": [],
		"system": [
			"3379792"
		]
	},
	"佳创视讯_2021-11-25下午6_16_51_-佳创视讯-300264": {
		"tradeInfoText": [],
		"tags": [],
		"system": [
			"3379792"
		]
	},
	"宁波方正_2021-11-25下午6_17_11_-宁波方正-300998": {
		"tags": [],
		"system": []
	},
	"恒信东方_2021-11-25下午6_17_38_-恒信东方-300081": {
		"tradeInfoText": [],
		"tags": [],
		"system": [
			"3379792"
		]
	},
	"中青宝_2021-11-25下午6_17_46_-中青宝-300052": {
		"tradeInfoText": [],
		"tags": [],
		"system": [
			"3379792"
		]
	},
	"宝通科技_2021-11-25下午6_18_00_-宝通科技-300031": {
		"tradeInfoText": [],
		"tags": [],
		"system": [
			"3379792"
		]
	},
	"上声电子_2021-11-25下午6_18_08_-上声电子-688533": {
		"tradeInfoText": [],
		"tags": [],
		"system": [
			"3379792"
		]
	},
	"宝鹰股份_2021-11-25下午6_18_17_-宝鹰股份-002047": {
		"tradeInfoText": [],
		"tags": [],
		"system": [
			"3379792"
		]
	},
	"万里扬_2021-11-25下午6_18_48_-万里扬-002434": {
		"tags": [],
		"system": []
	},
	"中捷精工_2021-11-25下午6_19_11_-中捷精工-301072": {
		"tradeInfoText": [],
		"tags": [],
		"system": [
			"3379792"
		]
	},
	"沪光股份_2021-11-25下午6_19_17_-沪光股份-605333": {
		"tradeInfoText": [],
		"tags": [],
		"system": [
			"3379792"
		]
	},
	"海源复材_2021-11-25下午6_20_41_-海源复材-002529": {
		"tradeInfoText": [],
		"tags": [],
		"system": [
			"3379792"
		]
	},
	"GQY视讯_2021-11-25下午6_24_00_-GQY视讯-300076": {
		"tags": [],
		"system": []
	},
	"兰卫医学_2021-11-25下午6_51_58_-兰卫医学-301060": {
		"tradeInfoText": [],
		"tags": [],
		"system": [
			"3379792"
		]
	},
	"康平科技_2021-11-25下午7_09_13_-康平科技-300907": {
		"tags": [],
		"system": []
	},
	"隆华新材_2021-11-25下午7_09_34_-隆华新材-301149": {
		"tags": [],
		"system": []
	},
	"英洛华_2021-11-25下午7_21_37_-英洛华-000795": {
		"tradeInfoText": [],
		"tags": [],
		"system": [
			"3379792"
		]
	},
	"西藏城投_2021-11-25下午7_28_59_-西藏城投-600773": {
		"tradeInfoText": [],
		"tags": [],
		"system": [
			"3379792"
		]
	},
	"许继电气_2021-11-25下午7_29_10_-许继电气-000400": {
		"tradeInfoText": [],
		"tags": [],
		"system": [
			"3379792"
		]
	},
	"九安医疗_2021-11-25下午7_41_46_-九安医疗-002432": {
		"tradeInfoText": [],
		"tags": [],
		"system": [
			"3379792",
			"6734208",
			"8415531",
			"2673493",
			"7108001",
			"id_1722170897004_67020"
		]
	},
	"国电南瑞_2021-11-25下午7_43_43_-国电南瑞-600406": {
		"tradeInfoText": [],
		"tags": [],
		"system": []
	},
	"宝胜股份_2021-11-25下午7_44_56_-宝胜股份-600973": {
		"tags": [],
		"system": []
	},
	"镇洋发展_2021-11-25下午7_44_59_-镇洋发展-603213": {
		"tradeInfoText": [],
		"tags": [],
		"system": [
			"3379792"
		]
	},
	"炬华科技_2021-11-25下午7_48_51_-炬华科技-300360": {
		"tags": [],
		"system": []
	},
	"正海磁材_2021-11-25下午7_48_57_-正海磁材-300224": {
		"tradeInfoText": [],
		"tags": [],
		"system": [
			"3379792"
		]
	},
	"金运激光_2021-11-25下午7_49_53_-金运激光-300220": {
		"tags": [],
		"system": []
	},
	"金银河_2021-11-25下午7_50_14_-金银河-300619": {
		"tradeInfoText": [],
		"tags": [],
		"system": [
			"3379792"
		]
	},
	"浙江黎明_2021-11-25下午7_57_42_-浙江黎明-603048": {
		"tags": [],
		"system": []
	},
	"大富科技_2021-11-25下午8_06_06_-大富科技-300134": {
		"tags": [],
		"system": []
	},
	"undefined_2021-11-25下午8_13_58_-undefined-undefined": {
		"tags": [],
		"system": []
	},
	"undefined_2021-11-25下午8_14_06_-undefined-undefined": {
		"tags": [],
		"system": []
	},
	"undefined_2021-11-25下午8_14_15_-undefined-undefined": {
		"tags": [],
		"system": []
	},
	"undefined_2021-11-25下午8_14_17_-undefined-undefined": {
		"tags": [],
		"system": []
	},
	"undefined_2021-11-25下午8_14_28_-undefined-undefined": {
		"tags": [],
		"system": []
	},
	"富瀚微_2021-11-26下午9_55_32_-富瀚微-300613": {
		"tags": [],
		"system": []
	},
	"镇洋发展_2021-11-26下午9_55_38_-镇洋发展-603213": {
		"tradeInfoText": [],
		"tags": [],
		"system": [
			"3379792"
		]
	},
	"中文在线_2021-11-26下午9_56_37_-中文在线-300364": {
		"tradeInfoText": [],
		"tags": [],
		"system": [
			"3379792"
		]
	},
	"春晖智控_2021-11-26下午9_57_03_-春晖智控-300943": {
		"tags": [],
		"system": []
	},
	"海兰信_2021-11-26下午9_57_15_-海兰信-300065": {
		"tradeInfoText": [],
		"tags": [],
		"system": [
			"3379792"
		]
	},
	"康平科技_2021-11-26下午9_57_22_-康平科技-300907": {
		"tags": [],
		"system": []
	},
	"C雅创_2021-11-26下午9_57_49_-C雅创-301099": {
		"tags": [],
		"system": []
	},
	"佳创视讯_2021-11-26下午9_58_55_-佳创视讯-300264": {
		"tradeInfoText": [],
		"tags": [],
		"system": [
			"3379792"
		]
	},
	"旗天科技_2021-11-26下午10_01_13_-旗天科技-300061": {
		"tradeInfoText": [],
		"tags": [],
		"system": []
	},
	"银河磁体_2021-11-26下午10_01_24_-银河磁体-300127": {
		"tags": [],
		"system": []
	},
	"久吾高科_2021-11-26下午10_01_59_-久吾高科-300631": {
		"tradeInfoText": [],
		"tags": [],
		"system": [
			"3379792"
		]
	},
	"金银河_2021-11-26下午10_02_11_-金银河-300619": {
		"tradeInfoText": [],
		"tags": [],
		"system": [
			"3379792"
		]
	},
	"鞍重股份_2021-11-26下午10_25_29_-鞍重股份-002667": {
		"tags": [],
		"system": []
	},
	"广晟有色_2021-11-26下午10_25_41_-广晟有色-600259": {
		"tags": [],
		"system": []
	},
	"大金重工_2021-11-26下午10_25_48_-大金重工-002487": {
		"tradeInfoText": [],
		"tags": [],
		"system": [
			"3379792",
			"8415531"
		]
	},
	"丰元股份_2021-11-26下午10_26_08_-丰元股份-002805": {
		"tradeInfoText": [],
		"tags": [],
		"system": [
			"3379792"
		]
	},
	"协鑫能科_2021-11-26下午10_26_28_-协鑫能科-002015": {
		"tradeInfoText": [],
		"tags": [],
		"system": [
			"3379792"
		]
	},
	"英洛华_2021-11-26下午10_26_30_-英洛华-000795": {
		"tradeInfoText": [],
		"tags": [],
		"system": [
			"3379792"
		]
	},
	"璞泰来_2021-11-26下午10_27_10_-璞泰来-603659": {
		"tags": [],
		"system": []
	},
	"盛新锂能_2021-11-26下午10_28_29_-盛新锂能-002240": {
		"tags": [],
		"system": []
	},
	"蓝色光标_2021-11-26下午10_28_58_-蓝色光标-300058": {
		"tags": [],
		"system": []
	},
	"西藏城投_2021-11-26下午10_29_13_-西藏城投-600773": {
		"tradeInfoText": [],
		"tags": [],
		"system": [
			"3379792"
		]
	},
	"包钢股份_2021-11-26下午10_29_21_-包钢股份-600010": {
		"tradeInfoText": [],
		"tags": [],
		"system": [
			"3379792"
		]
	},
	"山东威达_2021-11-26下午10_29_54_-山东威达-002026": {
		"tradeInfoText": [],
		"tags": [],
		"system": [
			"3379792"
		]
	},
	"爱旭股份_2021-11-26下午10_30_17_-爱旭股份-600732": {
		"tradeInfoText": [],
		"tags": [],
		"system": [
			"3379792"
		]
	},
	"东方电缆_2021-11-26下午10_30_43_-东方电缆-603606": {
		"tradeInfoText": [],
		"tags": [],
		"system": [
			"3379792"
		]
	},
	"中钨高新_2021-11-26下午10_30_58_-中钨高新-000657": {
		"tags": [],
		"system": []
	},
	"隆华新材_2021-11-26下午10_31_30_-隆华新材-301149": {
		"tags": [],
		"system": []
	},
	"中辰股份_2021-11-26下午10_32_27_-中辰股份-300933": {
		"tags": [],
		"system": []
	},
	"大富科技_2021-11-26下午10_32_53_-大富科技-300134": {
		"tags": [],
		"system": []
	},
	"九安医疗_2021-11-26下午10_32_56_-九安医疗-002432": {
		"tradeInfoText": [],
		"tags": [],
		"system": [
			"3379792",
			"6734208",
			"8415531",
			"2673493",
			"7108001"
		]
	},
	"国科微_2021-11-26下午10_33_01_-国科微-300672": {
		"tradeInfoText": [],
		"tags": [],
		"system": [
			"3379792"
		]
	},
	"国电南瑞_2021-11-26下午10_43_49_-国电南瑞-600406": {
		"tags": [],
		"system": []
	},
	"一汽富维_2021-11-26下午10_43_54_-一汽富维-600742": {
		"tradeInfoText": [],
		"tags": [],
		"system": [
			"3379792"
		]
	},
	"正海磁材_2021-11-26下午10_43_59_-正海磁材-300224": {
		"tradeInfoText": [],
		"tags": [],
		"system": [
			"3379792"
		]
	},
	"基蛋生物_2021-11-26下午10_45_08_-基蛋生物-603387": {
		"tags": [],
		"system": []
	},
	"许继电气_2021-11-26下午10_45_14_-许继电气-000400": {
		"tradeInfoText": [],
		"tags": [],
		"system": [
			"3379792"
		]
	},
	"舒泰神_2021-11-26下午10_45_37_-舒泰神-300204": {
		"tradeInfoText": [],
		"tags": [],
		"system": [
			"3379792"
		]
	},
	"众生药业_2021-11-26下午10_45_45_-众生药业-002317": {
		"tradeInfoText": [],
		"tags": [],
		"system": [
			"3379792"
		]
	},
	"天齐锂业_2021-11-26下午10_49_18_-天齐锂业-002466": {
		"tradeInfoText": [],
		"tags": [],
		"system": [
			"3379792"
		]
	},
	"北方稀土_2021-11-26下午10_49_23_-北方稀土-600111": {
		"tradeInfoText": [],
		"tags": [],
		"system": [
			"3379792"
		]
	},
	"清水源_2021-11-26下午10_49_56_-清水源-300437": {
		"tradeInfoText": [],
		"tags": [],
		"system": [
			"3379792"
		]
	},
	"undefined_2021-11-26下午10_50_12_-undefined-undefined": {
		"tags": [],
		"system": []
	},
	"undefined_2021-11-26下午10_50_14_-undefined-undefined": {
		"tags": [],
		"system": []
	},
	"undefined_2021-11-26下午10_50_22_-undefined-undefined": {
		"tags": [],
		"system": []
	},
	"undefined_2021-11-26下午10_50_44_-undefined-undefined": {
		"tags": [],
		"system": []
	},
	"undefined_2021-11-26下午10_50_50_-undefined-undefined": {
		"tags": [],
		"system": []
	},
	"undefined_2021-11-26下午10_51_02_-undefined-undefined": {
		"tags": [],
		"system": []
	},
	"undefined_2021-11-26下午10_51_06_-undefined-undefined": {
		"tags": [],
		"system": []
	},
	"大金重工_2021-11-29下午6_40_02_-大金重工-002487": {
		"tradeInfoText": [],
		"tags": [],
		"system": [
			"3379792",
			"8415531"
		]
	},
	"拓新药业_2021-11-29下午6_42_01_-拓新药业-301089": {
		"tradeInfoText": [],
		"tags": [],
		"system": [
			"3379792"
		]
	},
	"鹏辉能源_2021-11-29下午6_42_14_-鹏辉能源-300438": {
		"tradeInfoText": [],
		"tags": [],
		"system": [
			"3379792"
		]
	},
	"迦南科技_2021-11-29下午6_42_37_-迦南科技-300412": {
		"tags": [],
		"system": []
	},
	"德方纳米_2021-11-29下午6_43_00_-德方纳米-300769": {
		"tradeInfoText": [],
		"tags": [],
		"system": [
			"3379792"
		]
	},
	"兰卫医学_2021-11-29下午6_43_12_-兰卫医学-301060": {
		"tradeInfoText": [],
		"tags": [],
		"system": [
			"3379792"
		]
	},
	"旗天科技_2021-11-29下午6_43_43_-旗天科技-300061": {
		"tradeInfoText": [],
		"tags": [],
		"system": []
	},
	"横店东磁_2021-11-29下午6_44_20_-横店东磁-002056": {
		"tradeInfoText": [],
		"tags": [],
		"system": [
			"3379792"
		]
	},
	"九安医疗_2021-11-29下午6_44_26_-九安医疗-002432": {
		"tradeInfoText": [],
		"tags": [],
		"system": [
			"3379792",
			"6734208",
			"8415531",
			"2673493",
			"7108001"
		]
	},
	"钧达股份_2021-11-29下午6_44_46_-钧达股份-002865": {
		"tradeInfoText": [],
		"tags": [],
		"system": [
			"3379792",
			"6734208",
			"8415531",
			"3589400"
		]
	},
	"奥锐特_2021-11-29下午6_45_27_-奥锐特-605116": {
		"tags": [],
		"system": []
	},
	"融捷股份_2021-11-29下午6_45_45_-融捷股份-002192": {
		"tradeInfoText": [],
		"tags": [],
		"system": [
			"3379792"
		]
	},
	"中航重机_2021-11-29下午6_46_41_-中航重机-600765": {
		"tags": [],
		"system": []
	},
	"山东威达_2021-11-29下午6_46_49_-山东威达-002026": {
		"tradeInfoText": [],
		"tags": [],
		"system": [
			"3379792"
		]
	},
	"保隆科技_2021-11-29下午6_47_00_-保隆科技-603197": {
		"tradeInfoText": [],
		"tags": [],
		"system": [
			"3589400"
		]
	},
	"丰元股份_2021-11-29下午6_47_05_-丰元股份-002805": {
		"tradeInfoText": [],
		"tags": [],
		"system": [
			"3379792"
		]
	},
	"金圆股份_2021-11-29下午6_47_11_-金圆股份-000546": {
		"tradeInfoText": [],
		"tags": [],
		"system": [
			"3379792"
		]
	},
	"英洛华_2021-11-29下午6_47_45_-英洛华-000795": {
		"tradeInfoText": [],
		"tags": [],
		"system": [
			"3379792"
		]
	},
	"陕西金叶_2021-11-29下午6_48_08_-陕西金叶-000812": {
		"tradeInfoText": [],
		"tags": [],
		"system": [
			"3379792"
		]
	},
	"海联金汇_2021-11-29下午6_48_12_-海联金汇-002537": {
		"tags": [],
		"system": []
	},
	"盾安环境_2021-11-29下午6_48_52_-盾安环境-002011": {
		"tradeInfoText": [],
		"tags": [],
		"system": [
			"3379792"
		]
	},
	"中科电气_2021-11-29下午6_49_01_-中科电气-300035": {
		"tags": [],
		"system": []
	},
	"林洋能源_2021-11-29下午6_49_28_-林洋能源-601222": {
		"tradeInfoText": [],
		"tags": [],
		"system": []
	},
	"中钨高新_2021-11-29下午6_49_33_-中钨高新-000657": {
		"tradeInfoText": [],
		"tags": [],
		"system": [
			"3379792"
		]
	},
	"西藏珠峰_2021-11-29下午6_49_42_-西藏珠峰-600338": {
		"tradeInfoText": [],
		"tags": [],
		"system": [
			"3379792"
		]
	},
	"江特电机_2021-11-29下午6_49_52_-江特电机-002176": {
		"tradeInfoText": [],
		"tags": [],
		"system": [
			"3379792"
		]
	},
	"璞泰来_2021-11-29下午6_50_54_-璞泰来-603659": {
		"tradeInfoText": [],
		"tags": [],
		"system": [
			"3379792"
		]
	},
	"中辰股份_2021-11-29下午6_52_25_-中辰股份-300933": {
		"tags": [],
		"system": []
	},
	"蓝色光标_2021-11-29下午6_52_32_-蓝色光标-300058": {
		"tags": [],
		"system": []
	},
	"银河磁体_2021-11-29下午6_53_24_-银河磁体-300127": {
		"tags": [],
		"system": []
	},
	"镇洋发展_2021-11-29下午7_05_59_-镇洋发展-603213": {
		"tradeInfoText": [],
		"tags": [],
		"system": [
			"3379792"
		]
	},
	"许继电气_2021-11-29下午7_07_15_-许继电气-000400": {
		"tradeInfoText": [],
		"tags": [],
		"system": [
			"3379792"
		]
	},
	"清水源_2021-11-29下午7_07_40_-清水源-300437": {
		"tradeInfoText": [],
		"tags": [],
		"system": [
			"3379792"
		]
	},
	"undefined_2021-11-29下午8_52_53_-undefined-undefined": {
		"tags": [],
		"system": []
	},
	"undefined_2021-11-29下午8_53_00_-undefined-undefined": {
		"tags": [],
		"system": []
	},
	"undefined_2021-11-29下午8_53_05_-undefined-undefined": {
		"tags": [],
		"system": []
	},
	"undefined_2021-11-29下午8_53_09_-undefined-undefined": {
		"tags": [],
		"system": []
	},
	"undefined_2021-11-29下午8_53_19_-undefined-undefined": {
		"tags": [],
		"system": []
	},
	"西藏城投_2021-11-29下午10_05_53_-西藏城投-600773": {
		"tradeInfoText": [],
		"tags": [],
		"system": [
			"3379792"
		]
	},
	"天瑞仪器_2021-11-30下午9_32_26_-天瑞仪器-300165": {
		"tags": [],
		"system": []
	},
	"迦南科技_2021-11-30下午9_32_30_-迦南科技-300412": {
		"tags": [],
		"system": []
	},
	"任子行_2021-11-30下午9_33_12_-任子行-300311": {
		"tags": [],
		"system": []
	},
	"新国都_2021-11-30下午9_33_15_-新国都-300130": {
		"tags": [],
		"system": []
	},
	"兰卫医学_2021-11-30下午9_33_18_-兰卫医学-301060": {
		"tradeInfoText": [],
		"tags": [],
		"system": [
			"3379792"
		]
	},
	"深冷股份_2021-11-30下午9_33_21_-深冷股份-300540": {
		"tags": [],
		"system": []
	},
	"春晖智控_2021-11-30下午9_34_44_-春晖智控-300943": {
		"tags": [],
		"system": []
	},
	"财信发展_2021-11-30下午9_35_28_-财信发展-000838": {
		"tradeInfoText": [],
		"tags": [],
		"system": [
			"3379792"
		]
	},
	"尚荣医疗_2021-11-30下午9_35_58_-尚荣医疗-002551": {
		"tags": [],
		"system": []
	},
	"盾安环境_2021-11-30下午9_36_15_-盾安环境-002011": {
		"tradeInfoText": [],
		"tags": [],
		"system": [
			"3379792"
		]
	},
	"奥锐特_2021-11-30下午9_36_23_-奥锐特-605116": {
		"tags": [],
		"system": []
	},
	"新力金融_2021-11-30下午9_36_55_-新力金融-600318": {
		"tags": [],
		"system": []
	},
	"未名医药_2021-11-30下午9_37_00_-未名医药-002581": {
		"tags": [],
		"system": []
	},
	"宁波精达_2021-11-30下午9_37_14_-宁波精达-603088": {
		"tags": [],
		"system": []
	},
	"西陇科学_2021-11-30下午9_37_26_-西陇科学-002584": {
		"tags": [],
		"system": []
	},
	"九安医疗_2021-11-30下午9_37_42_-九安医疗-002432": {
		"tradeInfoText": [],
		"tags": [
			"2055992"
		],
		"system": [
			"3379792",
			"6734208",
			"8415531",
			"2673493",
			"7108001"
		]
	},
	"天神娱乐_2021-11-30下午9_38_15_-天神娱乐-002354": {
		"tags": [],
		"system": []
	},
	"海联金汇_2021-11-30下午9_38_25_-海联金汇-002537": {
		"tags": [],
		"system": []
	},
	"旗天科技_2021-11-30下午9_38_27_-旗天科技-300061": {
		"tradeInfoText": [],
		"tags": [],
		"system": []
	},
	"中捷精工_2021-11-30下午9_39_00_-中捷精工-301072": {
		"tradeInfoText": [],
		"tags": [],
		"system": [
			"3379792"
		]
	},
	"金圆股份_2021-11-30下午9_39_34_-金圆股份-000546": {
		"tradeInfoText": [],
		"tags": [],
		"system": [
			"3589400",
			"3379792"
		]
	},
	"中钨高新_2021-11-30下午9_40_22_-中钨高新-000657": {
		"tradeInfoText": [],
		"tags": [],
		"system": [
			"3379792"
		]
	},
	"镇洋发展_2021-11-30下午9_41_02_-镇洋发展-603213": {
		"tradeInfoText": [],
		"tags": [],
		"system": [
			"3379792"
		]
	},
	"中文在线_2021-11-30下午9_41_35_-中文在线-300364": {
		"tradeInfoText": [],
		"tags": [],
		"system": [
			"3379792"
		]
	},
	"大金重工_2021-11-30下午9_41_44_-大金重工-002487": {
		"tradeInfoText": [],
		"tags": [],
		"system": [
			"3379792",
			"8415531"
		]
	},
	"横店东磁_2021-11-30下午9_41_52_-横店东磁-002056": {
		"tradeInfoText": [],
		"tags": [],
		"system": [
			"3379792"
		]
	},
	"鹏辉能源_2021-11-30下午9_42_22_-鹏辉能源-300438": {
		"tradeInfoText": [],
		"tags": [],
		"system": [
			"3379792"
		]
	},
	"中航重机_2021-11-30下午9_42_40_-中航重机-600765": {
		"tradeInfoText": [],
		"tags": [],
		"system": [
			"3589400"
		]
	},
	"东方日升_2021-11-30下午9_42_43_-东方日升-300118": {
		"tradeInfoText": [],
		"tags": [],
		"system": [
			"3589400"
		]
	},
	"丰元股份_2021-11-30下午9_43_10_-丰元股份-002805": {
		"tradeInfoText": [],
		"tags": [],
		"system": [
			"3379792"
		]
	},
	"陕西金叶_2021-11-30下午9_43_20_-陕西金叶-000812": {
		"tradeInfoText": [],
		"tags": [],
		"system": [
			"3379792"
		]
	},
	"中国能建_2021-11-30下午9_43_53_-中国能建-601868": {
		"tags": [],
		"system": []
	},
	"拓新药业_2021-11-30下午9_44_02_-拓新药业-301089": {
		"tradeInfoText": [],
		"tags": [],
		"system": [
			"3379792"
		]
	},
	"英洛华_2021-11-30下午9_44_06_-英洛华-000795": {
		"tradeInfoText": [],
		"tags": [],
		"system": [
			"3379792"
		]
	},
	"中远海控_2021-11-30下午9_44_12_-中远海控-601919": {
		"tags": [],
		"system": []
	},
	"undefined_2021-11-30下午9_44_38_-undefined-undefined": {
		"tags": [],
		"system": []
	},
	"undefined_2021-11-30下午9_44_47_-undefined-undefined": {
		"tags": [],
		"system": []
	},
	"undefined_2021-11-30下午9_44_51_-undefined-undefined": {
		"tags": [],
		"system": []
	},
	"undefined_2021-11-30下午9_44_58_-undefined-undefined": {
		"tags": [],
		"system": []
	},
	"undefined_2021-11-30下午9_45_03_-undefined-undefined": {
		"tags": [],
		"system": []
	},
	"undefined_2021-11-30下午9_45_07_-undefined-undefined": {
		"tags": [],
		"system": []
	},
	"undefined_2021-11-30下午9_45_15_-undefined-undefined": {
		"tags": [],
		"system": []
	},
	"undefined_2021-11-30下午9_47_16_-undefined-undefined": {
		"tags": [],
		"system": []
	},
	"undefined_2021-11-30下午9_47_29_-undefined-undefined": {
		"tags": [],
		"system": []
	},
	"undefined_2021-11-30下午9_47_41_-undefined-undefined": {
		"tags": [],
		"system": []
	}
}